{"0": {"CONTENT": ["vous"], "MENTION_ID": "u-MENTION-adrouin_1338585337892", "START": "5", "END": "5", "SPAN-ID": "5-5"}, "1": {"CONTENT": ["la", "documentation", "hiver", "d\u00e9j\u00e0", "de", "l'", "Alpe", "d'", "Huez"], "MENTION_ID": "u-MENTION-adrouin_1338585346997", "START": "7", "END": "15", "SPAN-ID": "7-15"}, "2": {"CONTENT": ["la", "documentation", "hiver"], "MENTION_ID": "u-MENTION-jmuzerelle_1371112826055", "START": "7", "END": "9", "SPAN-ID": "7-9"}, "3": {"CONTENT": ["hiver"], "MENTION_ID": "u-MENTION-jmuzerelle_1371112668263", "START": "9", "END": "9", "SPAN-ID": "9-9"}, "4": {"CONTENT": ["l'", "Alpe", "d'", "Huez"], "MENTION_ID": "u-MENTION-adrouin_1338585359565", "START": "12", "END": "15", "SPAN-ID": "12-15"}, "5": {"CONTENT": ["Meg\u00e8ve"], "MENTION_ID": "u-MENTION-adrouin_1338585410908", "START": "17", "END": "17", "SPAN-ID": "17-17"}, "6": {"CONTENT": ["Valloire"], "MENTION_ID": "u-MENTION-adrouin_1338585423730", "START": "19", "END": "19", "SPAN-ID": "19-19"}, "7": {"CONTENT": ["Valloire"], "MENTION_ID": "u-MENTION-adrouin_1338585437732", "START": "20", "END": "20", "SPAN-ID": "20-20"}, "8": {"CONTENT": ["on"], "MENTION_ID": "u-MENTION-adrouin_1338585450877", "START": "21", "END": "21", "SPAN-ID": "21-21"}, "9": {"CONTENT": ["l'"], "MENTION_ID": "u-MENTION-adrouin_1338585508640", "START": "22", "END": "22", "SPAN-ID": "22-22"}, "10": {"CONTENT": ["Meg\u00e8ve"], "MENTION_ID": "u-MENTION-adrouin_1338585520896", "START": "26", "END": "26", "SPAN-ID": "26-26"}, "11": {"CONTENT": ["Alpe", "d'", "Huez"], "MENTION_ID": "u-MENTION-adrouin_1338585532767", "START": "27", "END": "29", "SPAN-ID": "27-29"}, "12": {"CONTENT": ["je"], "MENTION_ID": "u-MENTION-adrouin_1338585548780", "START": "32", "END": "32", "SPAN-ID": "32-32"}, "13": {"CONTENT": ["vous"], "MENTION_ID": "u-MENTION-adrouin_1338585553543", "START": "33", "END": "33", "SPAN-ID": "33-33"}}