{"0": "est", "1": "-ce", "2": "qu'", "3": "il", "4": "y", "5": "a", "6": "longtemps", "7": "que", "8": "vous", "9": "\u00eates", "10": "\u00e0", "11": "Orl\u00e9ans", "12": "monsieur", "13": "?", "14": "j'", "15": "y", "16": "suis", "17": "n\u00e9", "18": "ah", "19": "vous", "20": "\u00eates", "21": "n\u00e9", "22": "\u00e0", "23": "Orl\u00e9ans", "24": "?", "25": "oui", "26": "et", "27": "vous", "28": "vous", "29": "vous", "30": "vous", "31": "plaisez", "32": "\u00e0", "33": "Orl\u00e9ans", "34": "enfin", "35": "personnellement", "36": "?", "37": "oui", "38": "c'", "39": "est", "40": "une", "41": "ville", "42": "qui", "43": "est", "44": "et", "45": "euh", "46": "est", "47": "-ce", "48": "que", "49": "vous", "50": "pouvez", "51": "me", "52": "dire", "53": "donc", "54": "ce", "55": "que", "56": "vous", "57": "faites", "58": "comme", "59": "travail", "60": "enfin", "61": "vous", "62": "avez", "63": "dit", "64": "que", "65": "c'", "66": "est", "67": "?", "68": "au", "69": "Cepak", "70": "euh", "71": "qu'", "72": "est", "73": "-ce", "74": "que", "75": "qu'", "76": "est", "77": "-ce", "78": "que", "79": "c'", "80": "est", "81": "que", "82": "le", "83": "Cepak", "84": "si", "85": "vous", "86": "pouvez", "87": "m'", "88": "expliquer", "89": "et", "90": "puis", "91": "votre", "92": "travail", "93": "?", "94": "c'", "95": "est", "96": "une", "97": "soci\u00e9t\u00e9", "98": "qui", "99": "fait", "100": "de", "101": "l'", "102": "installation", "103": "et", "104": "de", "105": "l'", "106": "entretien", "107": "de", "108": "du", "109": "mat\u00e9riel", "110": "concernant", "111": "les", "112": "hydrocarbures", "113": "c'est-\u00e0-dire", "114": "qu'", "115": "on", "116": "installe", "117": "les", "118": "stations-services", "119": "on", "120": "construit", "121": "des", "122": "camions-citernes", "123": "hm", "124": "hm", "125": "on", "126": "construit", "127": "des", "128": "d\u00e9p\u00f4ts", "129": "de", "130": "carburants", "131": "aussi", "132": "hm", "133": "hm", "134": "enfin", "135": "tout", "136": "ce", "137": "qui", "138": "concerne", "139": "stockage", "140": "distribution", "141": "de", "142": "l'", "143": "hydrocarbure", "144": "ah", "145": "oui", "146": "d'", "147": "accord", "148": "et", "149": "est", "150": "-ce", "151": "que", "152": "\u00e7a", "153": "vous", "154": "avez", "155": "dit", "156": "que", "157": "\u00e7a", "158": "n'", "159": "a", "160": "rien", "161": "\u00e0", "162": "voir", "163": "avec", "164": "chez", "165": "Esso", "166": "est", "167": "-ce", "168": "que", "169": "c'", "170": "est", "171": "c'", "172": "est", "173": "pas", "174": "enfin", "175": "si", "176": "vous", "177": "vous", "178": "faites", "179": "des", "180": "constructions", "181": "de", "182": "citernes", "183": "et", "184": "tout", "185": "\u00e7a", "186": "c'", "187": "est", "188": "quand", "189": "m\u00eame", "190": "euh", "191": "\u00e7a", "192": "a", "193": "un", "194": "rapport", "195": "avec", "196": "la", "197": "fonderie", "198": "non", "199": "c'", "200": "est", "201": "simplement", "202": "euh", "203": "je", "204": "suis", "205": "un", "206": "Chenesseau", "207": "qui", "208": "se", "209": "trouve", "210": "\u00e0", "211": "la", "212": "t\u00eate", "213": "de", "214": "la", "215": "Cepak", "216": "mais", "217": "c'", "218": "est", "219": "tout", "220": "c'", "221": "est", "222": "tout", "223": "?", "224": "oui", "225": "hm", "226": "hm", "227": "et", "228": "c'", "229": "est", "230": "une", "231": "maison", "232": "qui", "233": "est", "234": "fond\u00e9e", "235": "depuis", "236": "longtemps", "237": "?", "238": "ou", "239": "depuis", "240": "dix", "241": "ans", "242": "seulement", "243": "hm", "244": "hm", "245": "et", "246": "vous", "247": "f-", "248": "votre", "249": "travail", "250": "consiste", "251": "en", "252": "quoi", "253": "ici", "254": "qu'", "255": "est", "256": "-ce", "257": "que", "258": "vous", "259": "?", "260": "dix", "261": "ans", "262": "ben", "263": "\u00e0", "264": "diriger", "265": "la", "266": "soci\u00e9t\u00e9", "267": "\u00e0", "268": "diriger", "269": "la", "270": "soci\u00e9t\u00e9", "271": "oui", "272": "et", "273": "cela", "274": "vous", "275": "enfin", "276": "vous", "277": "restez", "278": "surtout", "279": "\u00e0", "280": "Orl\u00e9ans", "281": "ou", "282": "est", "283": "-ce", "284": "que", "285": "vous", "286": "avez", "287": "beaucoup", "288": "de", "289": "d\u00e9placements", "290": "\u00e0", "291": "faire", "292": "?", "293": "euh", "294": "non", "295": "je", "296": "suis", "297": "tr\u00e8s", "298": "rarement", "299": "\u00e0", "300": "Orl\u00e9ans", "301": "parce", "302": "que", "303": "j'", "304": "ai", "305": "une", "306": "succursale", "307": "\u00e0", "308": "Paris", "309": "hm", "310": "hm", "311": "une", "312": "autre", "313": "\u00e0", "314": "Nantes", "315": "ah", "316": "oui", "317": "d'", "318": "accord", "319": "hm", "320": "hm", "321": "alors", "322": "vous", "323": "\u00eates", "324": "en", "325": "perp\u00e9tuel", "326": "d\u00e9placement", "327": "en", "328": "g\u00e9n\u00e9ral", "329": "oui", "330": "d\u00e9placement", "331": "oui", "332": "et", "333": "est", "334": "-ce", "335": "que", "336": "vous", "337": "pouvez", "338": "me", "339": "d\u00e9crire", "340": "une", "341": "journ\u00e9e", "342": "de", "343": "travail", "344": "comment", "345": "est", "346": "-ce", "347": "que", "348": "\u00e7a", "349": "se", "350": "passe", "351": "pour", "352": "vous", "353": "?", "354": "si", "355": "vous", "356": "voulez", "357": "j'", "358": "arrive", "359": "au", "360": "bureau", "361": "entre", "362": "euh", "363": "sept", "364": "heures", "365": "et", "366": "demie", "367": "et", "368": "huit", "369": "heures", "370": "hm", "371": "je", "372": "regarde", "373": "un", "374": "peu", "375": "le", "376": "disons", "377": "les", "378": "affaires", "379": "courantes", "380": "hm", "381": "hm", "382": "et", "383": "puis", "384": "le", "385": "plus", "386": "souvent", "387": "je", "388": "m'", "389": "en", "390": "vais", "391": "soit", "392": "\u00e0", "393": "Paris", "394": "euh", "395": "voir", "396": "des", "397": "clients", "398": "ou", "399": "je", "400": "tourne", "401": "un", "402": "peu", "403": "dans", "404": "le", "405": "dans", "406": "tout", "407": "le", "408": "secteur", "409": "o\u00f9", "410": "je", "411": "travaille", "412": "hm", "413": "hm", "414": "ou", "415": "bien", "416": "si", "417": "je", "418": "reste", "419": "ici", "420": "bon", "421": "ben", "422": "c'", "423": "est", "424": "tout", "425": "le", "426": "travail", "427": "de", "428": "de", "429": "bureau", "430": "d'", "431": "administration", "432": "normale", "433": "c'est-\u00e0-dire", "434": "euh", "435": "voir", "436": "la", "437": "comptabilit\u00e9", "438": "la", "439": "facturation", "440": "euh", "441": "hm", "442": "hm", "443": "et", "444": "cetera", "445": "oui", "446": "oui", "447": "et", "448": "vous", "449": "avez", "450": "d'", "451": "autres", "452": "personnes", "453": "qui", "454": "restent", "455": "euh", "456": "ici", "457": "tout", "458": "le", "459": "temps", "460": "pour", "461": "diriger", "462": "j'", "463": "ai", "464": "un", "465": "un", "466": "sous-directeur", "467": "qui", "468": "est", "469": "l\u00e0", "470": "en", "471": "permanence", "472": "hm", "473": "hm", "474": "bon", "475": "plus", "476": "tous", "477": "les", "478": "chefs", "479": "de", "480": "service", "481": "et", "482": "tout", "483": "\u00e7a", "484": "oui", "485": "oui", "486": "d'", "487": "accord", "488": "hm", "489": "hm", "490": "et", "491": "est", "492": "-ce", "493": "que", "494": "est", "495": "-ce", "496": "qu'", "497": "il", "498": "y", "499": "a", "500": "des", "501": "choses", "502": "qui", "503": "vous", "504": "plaisent", "505": "et", "506": "qui", "507": "vous", "508": "d\u00e9plaisent", "509": "dans", "510": "votre", "511": "travail", "512": "est", "513": "-ce", "514": "que", "515": "enfin", "516": "?", "517": "hm", "518": "je", "519": "crois", "520": "que", "521": "l'", "522": "ensemble", "523": "de", "524": "mon", "525": "travail", "526": "me", "527": "pla\u00eet", "528": "sans", "529": "\u00e7a", "530": "je", "531": "le", "532": "ferais", "533": "pas", "534": "oui", "535": "et", "536": "si", "537": "vous", "538": "n'", "539": "\u00e9tiez", "540": "pas", "541": "directeur", "542": "de", "543": "Cepak", "544": "enfin", "545": "si", "546": "vous", "547": "ne", "548": "faisiez", "549": "pas", "550": "le", "551": "m\u00e9tier", "552": "que", "553": "vous", "554": "faites", "555": "est", "556": "-ce", "557": "qu'", "558": "est", "559": "-ce", "560": "que", "561": "vous", "562": "auriez", "563": "aim\u00e9", "564": "faire", "565": "?", "566": "est", "567": "-ce", "568": "qu'", "569": "il", "570": "y", "571": "a", "572": "quelque", "573": "chose", "574": "que", "575": "?", "576": "non", "577": "muis", "578": "de", "579": "toute", "580": "fa\u00e7on", "581": "\u00e7a", "582": "aurait", "583": "\u00e9t\u00e9", "584": "dans", "585": "dans", "586": "une", "587": "entreprise", "588": "quelconque", "589": "si", "590": "hm", "591": "hm", "592": "c'", "593": "\u00e9tait", "594": "d\u00e8s", "595": "la", "596": "naissance", "597": "vous", "598": "vouliez", "599": "avoir", "600": "j'", "601": "aime", "602": "bien", "603": "les", "604": "le", "605": "travail", "606": "de", "607": "cr\u00e9ation", "608": "hm", "609": "hm", "610": "hm", "611": "et", "612": "de", "613": "plus", "614": "en", "615": "plus", "616": "de", "617": "femmes", "618": "mari\u00e9es", "619": "travaillent", "620": "aujourd'hui", "621": "est", "622": "-ce", "623": "que", "624": "vous", "625": "\u00eates", "626": "personnellement", "627": "pour", "628": "ou", "629": "contre", "630": "?", "631": "plut\u00f4t", "632": "pour", "633": "plut\u00f4t", "634": "pour", "635": "et", "636": "pourquoi", "637": "?", "638": "parce", "639": "que", "640": "\u00e7a", "641": "augmente", "642": "les", "643": "revenus", "644": "des", "645": "foyers", "646": "et", "647": "je", "648": "pense", "649": "que", "650": "c'", "651": "est", "652": "meilleur", "653": "hm", "654": "hm", "655": "vous", "656": "ne", "657": "voyez", "658": "rien", "659": "contre", "660": "enfin", "661": "une", "662": "femme", "663": "mari\u00e9e", "664": "avec", "665": "des", "666": "enfants", "667": "qui", "668": "travaille", "669": "c'", "670": "est", "671": "?", "672": "ah", "673": "\u00e0", "674": "partir", "675": "d'", "676": "un", "677": "certain", "678": "\u00e2ge", "679": "il", "680": "faut", "681": "quand", "682": "m\u00eame", "683": "que", "684": "la", "685": "femme", "686": "s'", "687": "occupe", "688": "de", "689": "ses", "690": "enfants", "691": "l\u00e0", "692": "c'", "693": "est", "694": "une", "695": "raison", "696": "d'", "697": "\u00e9ducation", "698": "si", "699": "c'", "700": "est", "701": "\u00e9lev\u00e9", "702": "par", "703": "une", "704": "nourrice", "705": "c'", "706": "est", "707": "s\u00fbrement", "708": "pas", "709": "euh", "710": "une", "711": "\u00e9ducation", "712": "normale", "713": "hm", "714": "hm", "715": "et", "716": "mais", "717": "quand", "718": "m\u00eame", "719": "euh", "720": "c'est-\u00e0-dire", "721": "entre", "722": "quatre", "723": "et", "724": "dix", "725": "ans", "726": "euh", "727": "au", "728": "point", "729": "de", "730": "vue", "731": "\u00e2ge", "732": "de", "733": "l'", "734": "enfant", "735": "hm", "736": "hm", "737": "\u00e0", "738": "mon", "739": "avis", "740": "faut", "741": "que", "742": "la", "743": "femme", "744": "reste", "745": "avec", "746": "eux", "747": "reste", "748": "avec", "749": "les", "750": "enfants", "751": "et", "752": "puis", "753": "plus", "754": "tard", "755": "oui", "756": "reprendre", "757": "le", "758": "travail", "759": "elle", "760": "reprend", "761": "le", "762": "travail", "763": "apr\u00e8s", "764": "et", "765": "qu'", "766": "est", "767": "-ce", "768": "que", "769": "vous", "770": "faites", "771": "de", "772": "votre", "773": "temps", "774": "libre", "775": "?", "776": "est", "777": "-ce", "778": "que", "779": "enfin", "780": "je", "781": "ne", "782": "sais", "783": "pas", "784": "si", "785": "vous", "786": "avez", "787": "beaucoup", "788": "de", "789": "temps", "790": "enfin", "791": "oui", "792": "mon", "793": "temps", "794": "libre", "795": "euh", "796": "si", "797": "le", "798": "week-end", "799": "est", "800": "assez", "801": "long", "802": "je", "803": "vais", "804": "au", "805": "bord", "806": "de", "807": "la", "808": "mer", "809": "je", "810": "fais", "811": "du", "812": "bateau", "813": "enfin", "814": "de", "815": "la", "816": "p\u00eache", "817": "hm", "818": "et", "819": "sinon", "820": "bon", "821": "ben", "822": "euh", "823": "de", "824": "la", "825": "chasse", "826": "et", "827": "quand", "828": "c'", "829": "est", "830": "ouvert", "831": "la", "832": "chasse", "833": "?", "834": "et", "835": "euh", "836": "le", "837": "soir", "838": "euh", "839": "?", "840": "ben", "841": "le", "842": "soir", "843": "euh", "844": "\u00e9tant", "845": "rarement", "846": "chez", "847": "moi", "848": "euh", "849": "quand", "850": "j'", "851": "y", "852": "suis", "853": "je", "854": "je", "855": "lis", "856": "un", "857": "peu", "858": "ou", "859": "hm", "860": "hm", "861": "et", "862": "comment", "863": "est", "864": "-ce", "865": "que", "866": "vous", "867": "avez", "868": "pass\u00e9", "869": "dimanche", "870": "dernier", "871": "?", "872": "dimanche", "873": "dernier", "874": "j'", "875": "\u00e9tais", "876": "au", "877": "bord", "878": "de", "879": "la", "880": "mer", "881": "vous", "882": "\u00e9tiez", "883": "au", "884": "bord", "885": "de", "886": "la", "887": "mer", "888": "et", "889": "qu'", "890": "est", "891": "-ce", "892": "que", "893": "vous", "894": "ferez", "895": "pendant", "896": "les", "897": "vacances", "898": "d'", "899": "\u00e9t\u00e9", "900": "?", "901": "toujours", "902": "au", "903": "bord", "904": "de", "905": "la", "906": "mer", "907": "toujours", "908": "au", "909": "bord", "910": "de", "911": "la", "912": "mer", "913": "vous", "914": "n'", "915": "aimez", "916": "pas", "917": "la", "918": "montagne", "919": "?", "920": "euh", "921": "la", "922": "montagne", "923": "l'", "924": "hiver", "925": "oui", "926": "oui", "927": "oui", "928": "?", "929": "mais", "930": "mais", "931": "l'", "932": "\u00e9t\u00e9", "933": "non", "934": "l'", "935": "\u00e9t\u00e9", "936": "non", "937": "et", "938": "si", "939": "vous", "940": "aviez", "941": "deux", "942": "heures", "943": "de", "944": "temps", "945": "libre", "946": "suppl\u00e9mentaire", "947": "par", "948": "jour", "949": "qu'", "950": "est", "951": "-ce", "952": "que", "953": "vous", "954": "feriez", "955": "de", "956": "ce", "957": "temps", "958": "libre", "959": "?", "960": "qu'", "961": "est", "962": "-ce", "963": "que", "964": "vous", "965": "feriez", "966": "j'", "967": "en", "968": "sais", "969": "rien", "970": "la", "971": "question", "972": "se", "973": "pose", "974": "pas", "975": "tellement", "976": "et", "977": "en", "978": "g\u00e9n\u00e9ral", "979": "je", "980": "finis", "981": "de", "982": "travailler", "983": "vers", "984": "huit", "985": "heures", "986": "le", "987": "soir", "988": "et", "989": "bien", "990": "que", "991": "le", "992": "bureau", "993": "soit", "994": "ferm\u00e9", "995": "\u00e0", "996": "six", "997": "heures", "998": "hm", "999": "hm", "1000": "alors", "1001": "si", "1002": "le", "1003": "bureau", "1004": "fermait", "1005": "\u00e0", "1006": "quatre", "1007": "heures", "1008": "je", "1009": "pense", "1010": "que", "1011": "\u00e7a", "1012": "changerait", "1013": "quand", "1014": "m\u00eame", "1015": "rien", "1016": "de", "1017": "toute", "1018": "fa\u00e7on", "1019": "je", "1020": "reste", "1021": "jusqu'", "1022": "\u00e0", "1023": "huit", "1024": "heures", "1025": "oui", "1026": "oui", "1027": "et", "1028": "\u00e0", "1029": "votre", "1030": "avis", "1031": "qu'", "1032": "est", "1033": "-ce", "1034": "qu'", "1035": "on", "1036": "devrait", "1037": "surtout", "1038": "apprendre", "1039": "aux", "1040": "enfants", "1041": "\u00e0", "1042": "l'", "1043": "\u00e9cole", "1044": "est", "1045": "-ce", "1046": "qu'", "1047": "y", "1048": "a", "1049": "des", "1050": "choses", "1051": "qui", "1052": "euh", "1053": "sont", "1054": "selon", "1055": "vous", "1056": "plus", "1057": "importantes", "1058": "que", "1059": "d'", "1060": "autres", "1061": "ou", "1062": "?", "1063": "ben", "1064": "y", "1065": "a", "1066": "des", "1067": "choses", "1068": "qui", "1069": "apprendre", "1070": "les", "1071": "les", "1072": "langues", "1073": "\u00e9trang\u00e8res", "1074": "tr\u00e8s", "1075": "t\u00f4t", "1076": "parce", "1077": "que", "1078": "lorsqu'", "1079": "ils", "1080": "ont", "1081": "quatre", "1082": "ou", "1083": "cinq", "1084": "ans", "1085": "ils", "1086": "sont", "1087": "tr\u00e8s", "1088": "tr\u00e8s", "1089": "r\u00e9ceptifs", "1090": "aux", "1091": "aux", "1092": "langues", "1093": "\u00e7a", "1094": "les", "1095": "choque", "1096": "pas", "1097": "du", "1098": "tout", "1099": "et", "1100": "je", "1101": "pense", "1102": "que", "1103": "\u00e7a", "1104": "c'", "1105": "est", "1106": "une", "1107": "\u00e9duca-", "1108": "une", "1109": "lacune", "1110": "dans", "1111": "l'", "1112": "\u00e9ducation", "1113": "fran\u00e7aise", "1114": "c'", "1115": "est", "1116": "que", "1117": "on", "1118": "on", "1119": "ne", "1120": "poss\u00e8de", "1121": "pas", "1122": "les", "1123": "langues", "1124": "\u00e9trang\u00e8res", "1125": "vous", "1126": "croyez", "1127": "hm", "1128": "hm", "1129": "et", "1130": "d'", "1131": "autres", "1132": "choses", "1133": "?", "1134": "d'", "1135": "autres", "1136": "choses", "1137": "euh", "1138": "non", "1139": "je", "1140": "pense", "1141": "que", "1142": "le", "1143": "le", "1144": "syst\u00e8me", "1145": "d'", "1146": "instruction", "1147": "en", "1148": "France", "1149": "est", "1150": "tr\u00e8s", "1151": "g\u00e9n\u00e9ral", "1152": "hm", "1153": "hm", "1154": "euh", "1155": "ce", "1156": "qui", "1157": "fait", "1158": "que", "1159": "quand", "1160": "on", "1161": "sort", "1162": "de", "1163": "l'", "1164": "\u00e9cole", "1165": "on", "1166": "sait", "1167": "\u00e0", "1168": "peu", "1169": "pr\u00e8s", "1170": "rien", "1171": "mais", "1172": "enfin", "1173": "on", "1174": "sait", "1175": "\u00e0", "1176": "la", "1177": "fois", "1178": "aussi", "1179": "beaucoup", "1180": "de", "1181": "choses", "1182": "et", "1183": "que", "1184": "c'", "1185": "est", "1186": "c'", "1187": "est", "1188": "pas", "1189": "mal", "1190": "dans", "1191": "le", "1192": "fond", "1193": "hm", "1194": "hm", "1195": "\u00e7a", "1196": "ouvre", "1197": "l'", "1198": "esprit", "1199": "sur", "1200": "beaucoup", "1201": "de", "1202": "choses", "1203": "oui", "1204": "oui", "1205": "et", "1206": "que", "1207": "pensez-", "1208": "vous", "1209": "du", "1210": "latin", "1211": "\u00e0", "1212": "l'", "1213": "\u00e9cole", "1214": "est", "1215": "-ce", "1216": "que", "1217": "?", "1218": "\u00e7a", "1219": "du", "1220": "latin", "1221": "euh", "1222": "\u00e7a", "1223": "a", "1224": "un", "1225": "gros", "1226": "avantage", "1227": "c'", "1228": "est", "1229": "que", "1230": "\u00e7a", "1231": "apprend", "1232": "\u00e0", "1233": "parler", "1234": "fran\u00e7ais", "1235": "le", "1236": "latin", "1237": "hm", "1238": "et", "1239": "que", "1240": "ben", "1241": "de", "1242": "moins", "1243": "en", "1244": "moins", "1245": "on", "1246": "trouve", "1247": "des", "1248": "des", "1249": "personnes", "1250": "qui", "1251": "qui", "1252": "savent", "1253": "parler", "1254": "un", "1255": "ou", "1256": "\u00e9-", "1257": "\u00e9crire", "1258": "un", "1259": "fran\u00e7ais", "1260": "correct", "1261": "hm", "1262": "hm", "1263": "et", "1264": "vous", "1265": "croyez", "1266": "que", "1267": "m\u00eame", "1268": "pour", "1269": "cela", "1270": "il", "1271": "aurait", "1272": "fallu", "1273": "garder", "1274": "le", "1275": "latin", "1276": "\u00e0", "1277": "l'", "1278": "\u00e9cole", "1279": "parce", "1280": "que", "1281": "y", "1282": "a", "1283": "toute", "1284": "une", "1285": "ben", "1286": "pour", "1287": "ceux", "1288": "qui", "1289": "auront", "1290": "\u00e0", "1291": "utiliser", "1292": "leur", "1293": "langue", "1294": "euh", "1295": "plus", "1296": "tard", "1297": "c'est-\u00e0-dire", "1298": "par", "1299": "exemple", "1300": "pour", "1301": "un", "1302": "chef", "1303": "d'", "1304": "entreprise", "1305": "\u00e0", "1306": "mon", "1307": "avis", "1308": "c'", "1309": "est", "1310": "indispensable", "1311": "parce", "1312": "qu'", "1313": "il", "1314": "faut", "1315": "savoir", "1316": "\u00e9crire", "1317": "euh", "1318": "hm", "1319": "hm", "1320": "correct", "1321": "oui", "1322": "\u00e9crire", "1323": "un", "1324": "fran\u00e7ais", "1325": "parfait", "1326": "hm", "1327": "hm", "1328": "\u00e7a", "1329": "fait", "1330": "pas", "1331": "tr\u00e8s", "1332": "s\u00e9rieux", "1333": "quand", "1334": "vous", "1335": "recevez", "1336": "une", "1337": "lettre", "1338": "qui", "1339": "est", "1340": "r\u00e9dig\u00e9e", "1341": "en", "1342": "avec", "1343": "des", "1344": "des", "1345": "fautes", "1346": "partout", "1347": "et", "1348": "dans", "1349": "quelles", "1350": "mati\u00e8res", "1351": "est", "1352": "-ce", "1353": "est-", "1354": "il", "1355": "bon", "1356": "qu'", "1357": "un", "1358": "enfant", "1359": "soit", "1360": "fort", "1361": "\u00e0", "1362": "l'", "1363": "\u00e9cole", "1364": "est", "1365": "-ce", "1366": "que", "1367": "y", "1368": "a", "1369": "des", "1370": "mati\u00e8res", "1371": "?", "1372": "euh", "1373": "ben", "1374": "actuellement", "1375": "le", "1376": "la", "1377": "la", "1378": "vie", "1379": "devient", "1380": "de", "1381": "plus", "1382": "en", "1383": "plus", "1384": "technique", "1385": "alors", "1386": "vaut", "1387": "mieux", "1388": "qu'", "1389": "il", "1390": "soit", "1391": "fort", "1392": "en", "1393": "maths", "1394": "hm", "1395": "hm", "1396": "euh", "1397": "mais", "1398": "il", "1399": "para\u00eet", "1400": "que", "1401": "en", "1402": "France", "1403": "les", "1404": "\u00e9coles", "1405": "enfin", "1406": "les", "1407": "lyc\u00e9es", "1408": "techniques", "1409": "sont", "1410": "un", "1411": "peu", "1412": "euh", "1413": "un", "1414": "peu", "1415": "faibles", "1416": "?", "1417": "oui", "1418": "enfin", "1419": "pas", "1420": "pas", "1421": "faibles", "1422": "mais", "1423": "un", "1424": "peu", "1425": "euh", "1426": "m\u00e9pris\u00e9s", "1427": "on", "1428": "m'", "1429": "a", "1430": "dit", "1431": "que", "1432": "oui", "1433": "c'", "1434": "est", "1435": "exact", "1436": "tout", "1437": "tout", "1438": "si", "1439": "vous", "1440": "voulez", "1441": "euh", "1442": "oh", "1443": "c'", "1444": "est", "1445": "que", "1446": "tous", "1447": "les", "1448": "gens", "1449": "voudraient", "1450": "que", "1451": "leur", "1452": "que", "1453": "leur", "1454": "gosse", "1455": "soit", "1456": "euh", "1457": "toubib", "1458": "ou", "1459": "avocat", "1460": "ou", "1461": "quelque", "1462": "chose", "1463": "comme", "1464": "\u00e7a", "1465": "mais", "1466": "c'", "1467": "est", "1468": "pas", "1469": "possible", "1470": "hm", "1471": "hm", "1472": "mais", "1473": "vous", "1474": "croyez", "1475": "que", "1476": "\u00e7a", "1477": "va", "1478": "changer", "1479": "enfin", "1480": "puisque", "1481": "ils", "1482": "vont", "1483": "accepter", "1484": "vous", "1485": "savez", "1486": "y", "1487": "a", "1488": "quand", "1489": "m\u00eame", "1490": "une", "1491": "question", "1492": "de", "1493": "revenus", "1494": "qui", "1495": "compte", "1496": "et", "1497": "euh", "1498": "actuellement", "1499": "une", "1500": "bonne", "1501": "coiffeuse", "1502": "doit", "1503": "gagner", "1504": "presque", "1505": "autant", "1506": "qu'", "1507": "un", "1508": "docteur", "1509": "donc", "1510": "les", "1511": "gens", "1512": "s'", "1513": "en", "1514": "apercevront", "1515": "bien", "1516": "un", "1517": "jour", "1518": "oui", "1519": "oui", "1520": "et", "1521": "qu'", "1522": "est", "1523": "-ce", "1524": "qui", "1525": "fait", "1526": "que", "1527": "les", "1528": "enfants", "1529": "r\u00e9ussissent", "1530": "ou", "1531": "ne", "1532": "r\u00e9ussissent", "1533": "pas", "1534": "\u00e0", "1535": "l'", "1536": "\u00e9cole", "1537": "?", "1538": "ah", "1539": "je", "1540": "crois", "1541": "que", "1542": "y", "1543": "a", "1544": "une", "1545": "grosse", "1546": "question", "1547": "de", "1548": "d'", "1549": "intelligence", "1550": "au", "1551": "d\u00e9part", "1552": "hm", "1553": "hm", "1554": "et", "1555": "puis", "1556": "ensuite", "1557": "il", "1558": "y", "1559": "a", "1560": "une", "1561": "question", "1562": "de", "1563": "de", "1564": "milieu", "1565": "familial", "1566": "qui", "1567": "les", "1568": "les", "1569": "pousse", "1570": "plus", "1571": "ou", "1572": "moins", "1573": "et", "1574": "qui", "1575": "les", "1576": "qui", "1577": "leur", "1578": "fait", "1579": "r\u00e9aliser", "1580": "ou", "1581": "pas", "1582": "la", "1583": "valeur", "1584": "du", "1585": "travail", "1586": "hm", "1587": "hm", "1588": "oui", "1589": "oui", "1590": "et", "1591": "jusqu'", "1592": "\u00e0", "1593": "quel", "1594": "\u00e2ge", "1595": "est", "1596": "-ce", "1597": "qu'", "1598": "il", "1599": "faudrait", "1600": "que", "1601": "les", "1602": "enfants", "1603": "continuent", "1604": "les", "1605": "en-", "1606": "leurs", "1607": "\u00e9tudes", "1608": "?", "1609": "actuellement", "1610": "la", "1611": "la", "1612": "scolarit\u00e9", "1613": "est", "1614": "obligatoire", "1615": "jusqu'", "1616": "\u00e0", "1617": "seize", "1618": "ans", "1619": "ou", "1620": "dix-huit", "1621": "ans", "1622": "je", "1623": "sais", "1624": "pas", "1625": "je", "1626": "crois", "1627": "seize", "1628": "ans", "1629": "seize", "1630": "ans", "1631": "oui", "1632": "c'", "1633": "est", "1634": "une", "1635": "bonne", "1636": "chose", "1637": "quoique", "1638": "euh", "1639": "certains", "1640": "ne", "1641": "font", "1642": "jamais", "1643": "rien", "1644": "\u00e0", "1645": "\u00e0", "1646": "l'", "1647": "\u00e9cole", "1648": "et", "1649": "leur", "1650": "faire", "1651": "perdre", "1652": "deux", "1653": "ans", "1654": "de", "1655": "plus", "1656": "l\u00e0", "1657": "euh", "1658": "\u00e7a", "1659": "a", "1660": "une", "1661": "utilit\u00e9", "1662": "euh", "1663": "hm", "1664": "m\u00e9diocre", "1665": "ah", "1666": "oui", "1667": "mais", "1668": "enfin", "1669": "c'", "1670": "est", "1671": "tout", "1672": "de", "1673": "m\u00eame", "1674": "une", "1675": "bonne", "1676": "chose", "1677": "de", "1678": "rendre", "1679": "\u00e7a", "1680": "obligatoire", "1681": "parce", "1682": "que", "1683": "l'", "1684": "ensemble", "1685": "des", "1686": "enfants", "1687": "a", "1688": "quand", "1689": "m\u00eame", "1690": "quelque", "1691": "chose", "1692": "\u00e0", "1693": "apprendre", "1694": "hm", "1695": "hm", "1696": "et", "1697": "vous", "1698": "croyez", "1699": "que", "1700": "jusqu'", "1701": "\u00e0", "1702": "seize", "1703": "ans", "1704": "ils", "1705": "peu-", "1706": "ils", "1707": "enfin", "1708": "\u00e7a", "1709": "va", "1710": "vous", "1711": "euh", "1712": "s-", "1713": "vous", "1714": "seriez", "1715": "favorable", "1716": "\u00e0", "1717": "une", "1718": "augmentation", "1719": "jusqu'", "1720": "\u00e0", "1721": "dix-huit", "1722": "ans", "1723": "?", "1724": "ben", "1725": "disons", "1726": "pour", "1727": "ceux", "1728": "qui", "1729": "se", "1730": "qui", "1731": "r\u00e9ussissent", "1732": "oui", "1733": "mais", "1734": "pour", "1735": "les", "1736": "autres", "1737": "euh", "1738": "non", "1739": "vaut", "1740": "quand", "1741": "m\u00eame", "1742": "mieux", "1743": "les", "1744": "orienter", "1745": "tout", "1746": "de", "1747": "suite", "1748": "vers", "1749": "un", "1750": "travail", "1751": "manuel", "1752": "si", "1753": "c'", "1754": "est", "1755": "\u00e7a", "1756": "qui", "1757": "leur", "1758": "pla\u00eet", "1759": "et", "1760": "si", "1761": "si", "1762": "c'", "1763": "est", "1764": "l\u00e0", "1765": "o\u00f9", "1766": "ils", "1767": "doivent", "1768": "r\u00e9ussir", "1769": "hm", "1770": "hm", "1771": "oui", "1772": "oui", "1773": "et", "1774": "vous", "1775": "croyez", "1776": "que", "1777": "les", "1778": "filles", "1779": "et", "1780": "les", "1781": "gar\u00e7ons", "1782": "doivent", "1783": "recevoir", "1784": "la", "1785": "m\u00eame", "1786": "\u00e9ducation", "1787": "enfin", "1788": "la", "1789": "m\u00eame", "1790": "instruction", "1791": "?", "1792": "c'", "1793": "est", "1794": "pareil", "1795": "oui", "1796": "oui", "1797": "oui", "1798": "euh", "1799": "et", "1800": "pour", "1801": "revenir", "1802": "\u00e0", "1803": "la", "1804": "ville", "1805": "d'", "1806": "Orl\u00e9ans", "1807": "est", "1808": "-ce", "1809": "que", "1810": "d'", "1811": "apr\u00e8s", "1812": "vous", "1813": "on", "1814": "fait", "1815": "assez", "1816": "pour", "1817": "les", "1818": "habitants", "1819": "\u00e0", "1820": "Orl\u00e9ans", "1821": "?", "1822": "ah", "1823": "\u00e7a", "1824": "c'", "1825": "est", "1826": "une", "1827": "un", "1828": "grand", "1829": "probl\u00e8me", "1830": "\u00e7a", "1831": "non", "1832": "non", "1833": "il", "1834": "faut", "1835": "qu'", "1836": "il", "1837": "y", "1838": "ait", "1839": "pas", "1840": "de", "1841": "y", "1842": "a", "1843": "pas", "1844": "de", "1845": "piscine", "1846": "couverte", "1847": "il", "1848": "va", "1849": "y", "1850": "en", "1851": "avoir", "1852": "une", "1853": "mais", "1854": "y", "1855": "en", "1856": "aura", "1857": "que", "1858": "jamais", "1859": "qu'", "1860": "une", "1861": "pour", "1862": "euh", "1863": "une", "1864": "agglom\u00e9ration", "1865": "qui", "1866": "doit", "1867": "grouper", "1868": "euh", "1869": "cent", "1870": "quarante", "1871": "mille", "1872": "habitants", "1873": "quelque", "1874": "chose", "1875": "comme", "1876": "\u00e7a", "1877": "hm", "1878": "hm", "1879": "c'", "1880": "est", "1881": "quand", "1882": "m\u00eame", "1883": "beaucoup", "1884": "trop", "1885": "peu", "1886": "y", "1887": "a", "1888": "un", "1889": "\u00e9quipement", "1890": "sportif", "1891": "qui", "1892": "est", "1893": "ridicule", "1894": "hm", "1895": "hm", "1896": "et", "1897": "sur", "1898": "d'", "1899": "autres", "1900": "plans", "1901": "?", "1902": "ben", "1903": "sportif", "1904": "et", "1905": "en", "1906": "loisirs", "1907": "en", "1908": "g\u00e9n\u00e9ral", "1909": "c'", "1910": "est", "1911": "c'", "1912": "est", "1913": "tr\u00e8s", "1914": "tr\u00e8s", "1915": "incomplet", "1916": "hm", "1917": "hm", "1918": "et", "1919": "enfin", "1920": "et", "1921": "enfin", "1922": "cin\u00e9mas", "1923": "y", "1924": "en", "1925": "a", "1926": "ben", "1927": "cin\u00e9ma", "1928": "ouais", "1929": "c-", "1930": "y", "1931": "a", "1932": "y", "1933": "a", "1934": "quatre", "1935": "cin\u00e9mas", "1936": "pour", "1937": "euh", "1938": "oui", "1939": "oui", "1940": "cent", "1941": "mille", "1942": "habitants", "1943": "oui", "1944": "quand", "1945": "m\u00eame", "1946": "hm", "1947": "hm", "1948": "un", "1949": "th\u00e9\u00e2tre", "1950": "qu'", "1951": "est", "1952": "inutilisable", "1953": "euh", "1954": "oui", "1955": "oui", "1956": "et", "1957": "nous", "1958": "avons", "1959": "dit", "1960": "on", "1961": "mais", "1962": "on", "1963": "\u00e7a", "1964": "repr\u00e9sente", "1965": "qui", "1966": "pour", "1967": "vous", "1968": "enfin", "1969": "quand", "1970": "je", "1971": "vous", "1972": "ai", "1973": "pos\u00e9", "1974": "la", "1975": "question", "1976": "j'", "1977": "ai", "1978": "demand\u00e9", "1979": "si", "1980": "on", "1981": "fait", "1982": "assez", "1983": "pour", "1984": "les", "1985": "habitants", "1986": "?", "1987": "ben", "1988": "c'", "1989": "est", "1990": "quand", "1991": "m\u00eame", "1992": "les", "1993": "\u00e9lus", "1994": "locaux", "1995": "c'", "1996": "est", "1997": "le", "1998": "conseil", "1999": "municipal", "2000": "dans", "2001": "son", "2002": "ensemble", "2003": "hm", "2004": "hm", "2005": "et", "2006": "vous", "2007": "croyez", "2008": "qu'", "2009": "il", "2010": "y", "2011": "a", "2012": "d'", "2013": "autres", "2014": "personnes", "2015": "qui", "2016": "ont", "2017": "de", "2018": "l'", "2019": "influence", "2020": "\u00e0", "2021": "part", "2022": "le", "2023": "conseil", "2024": "municipal", "2025": "\u00e0", "2026": "Orl\u00e9ans", "2027": "?", "2028": "franchement", "2029": "j'", "2030": "en", "2031": "sais", "2032": "rien", "2033": "non", "2034": "vous", "2035": "voyez", "2036": "pas", "2037": "d'", "2038": "autres", "2039": "euh", "2040": "?", "2041": "non", "2042": "les", "2043": "les", "2044": "c'", "2045": "est", "2046": "surtout", "2047": "eux", "2048": "qui", "2049": "dirigent", "2050": "euh", "2051": "oui", "2052": "la", "2053": "chambre", "2054": "de", "2055": "commerce", "2056": "est", "2057": "quand", "2058": "m\u00eame", "2059": "tr\u00e8s", "2060": "sp\u00e9cialis\u00e9e", "2061": "dans", "2062": "le", "2063": "dans", "2064": "le", "2065": "commerce", "2066": "et", "2067": "l'", "2068": "industrie", "2069": "donc", "2070": "euh", "2071": "je", "2072": "crois", "2073": "pas", "2074": "qu'", "2075": "ils", "2076": "puissent", "2077": "beaucoup", "2078": "influencer", "2079": "hm", "2080": "hm", "2081": "et", "2082": "on", "2083": "a", "2084": "beaucoup", "2085": "parl\u00e9", "2086": "d-", "2087": "des", "2088": "\u00e9v\u00e9nements", "2089": "de", "2090": "mai", "2091": "soixante-huit", "2092": "hm", "2093": "hm", "2094": "est", "2095": "-ce", "2096": "que", "2097": "vous", "2098": "pourriez", "2099": "m'", "2100": "expliquer", "2101": "\u00e0", "2102": "peu", "2103": "pr\u00e8s", "2104": "ce", "2105": "qui", "2106": "s'", "2107": "est", "2108": "pass\u00e9", "2109": "?", "2110": "enfin", "2111": "j'", "2112": "\u00e9tais", "2113": "pas", "2114": "en", "2115": "France", "2116": "\u00e0", "2117": "l'", "2118": "\u00e9poque", "2119": "l'", "2120": "\u00e9-", "2121": "l'", "2122": "\u00e9quipe", "2123": "n'", "2124": "\u00e9tait", "2125": "pas", "2126": "en", "2127": "France", "2128": "\u00e0", "2129": "l'", "2130": "\u00e9poque", "2131": "est", "2132": "-ce", "2133": "que", "2134": "ben", "2135": "ce", "2136": "qui", "2137": "s'", "2138": "est", "2139": "pass\u00e9", "2140": "c'", "2141": "\u00e9tait", "2142": "un", "2143": "oh", "2144": "je", "2145": "sais", "2146": "pas", "2147": "si", "2148": "c'", "2149": "est", "2150": "la", "2151": "v\u00e9rit\u00e9", "2152": "mais", "2153": "enfin", "2154": "c'", "2155": "\u00e9tait", "2156": "un", "2157": "mouvement", "2158": "d'", "2159": "\u00e9tudiants", "2160": "qui", "2161": "a", "2162": "d\u00e9g\u00e9n\u00e9r\u00e9", "2163": "en", "2164": "en", "2165": "gr\u00e8ve", "2166": "euh", "2167": "strictement", "2168": "revendicative", "2169": "sur", "2170": "un", "2171": "plan", "2172": "de", "2173": "salaire", "2174": "hm", "2175": "hm", "2176": "et", "2177": "\u00e7a", "2178": "a", "2179": "\u00e9t\u00e9", "2180": "tr\u00e8s", "2181": "amplifi\u00e9", "2182": "et", "2183": "tr\u00e8s", "2184": "pouss\u00e9", "2185": "par", "2186": "euh", "2187": "tous", "2188": "les", "2189": "moyens", "2190": "d'", "2191": "information", "2192": "que", "2193": "ce", "2194": "soit", "2195": "la", "2196": "presse", "2197": "ou", "2198": "la", "2199": "radio", "2200": "hm", "2201": "hm", "2202": "en", "2203": "tirer", "2204": "des", "2205": "des", "2206": "le\u00e7ons", "2207": "profondes", "2208": "c'", "2209": "est", "2210": "pas", "2211": "c'", "2212": "est", "2213": "pas", "2214": "facile", "2215": "je", "2216": "crois", "2217": "que", "2218": "hm", "2219": "hm", "2220": "et", "2221": "est", "2222": "-ce", "2223": "que", "2224": "vous", "2225": "voyez", "2226": "comment", "2227": "on", "2228": "peut", "2229": "expliquer", "2230": "les", "2231": "\u00e9v\u00e9nements", "2232": "?", "2233": "est", "2234": "-ce", "2235": "qu'", "2236": "y", "2237": "a", "2238": "une", "2239": "raison", "2240": "qui", "2241": "?", "2242": "donc", "2243": "y", "2244": "avait", "2245": "un", "2246": "m\u00e9contentement", "2247": "des", "2248": "\u00e9tudiants", "2249": "et", "2250": "que", "2251": "on", "2252": "les", "2253": "a", "2254": "peut-\u00eatre", "2255": "pris", "2256": "un", "2257": "peu", "2258": "trop", "2259": "au", "2260": "s\u00e9rieux", "2261": "hm", "2262": "hm", "2263": "ah", "2264": "les", "2265": "ouvriers", "2266": "que", "2267": "et", "2268": "au", "2269": "au", "2270": "point", "2271": "de", "2272": "vue", "2273": "social", "2274": "euh", "2275": "bien", "2276": "s\u00fbr", "2277": "au", "2278": "point", "2279": "de", "2280": "vue", "2281": "social", "2282": "c'", "2283": "est", "2284": "toujours", "2285": "justifi\u00e9", "2286": "les", "2287": "les", "2288": "mouvements", "2289": "hm", "2290": "hm", "2291": "n'", "2292": "y", "2293": "aurait", "2294": "pas", "2295": "eu", "2296": "de", "2297": "l'", "2298": "information", "2299": "pour", "2300": "euh", "2301": "pousser", "2302": "ce", "2303": "mouvement", "2304": "\u00e7a", "2305": "n'", "2306": "aurait", "2307": "jamais", "2308": "eu", "2309": "une", "2310": "ampleur", "2311": "pareille", "2312": "hm", "2313": "hm", "2314": "bon", "2315": "les", "2316": "cons\u00e9quences", "2317": "c'", "2318": "est", "2319": "que", "2320": "\u00e7a", "2321": "a", "2322": "fait", "2323": "prendre", "2324": "confiance", "2325": "conscience", "2326": "aux", "2327": "gens", "2328": "que", "2329": "bon", "2330": "qu'", "2331": "\u00e0", "2332": "son", "2333": "tour", "2334": "on", "2335": "arrivait", "2336": "\u00e0", "2337": "ce", "2338": "qu'", "2339": "on", "2340": "voulait", "2341": "oui", "2342": "oh", "2343": "c'", "2344": "est", "2345": "c'", "2346": "est", "2347": "la", "2348": "seule", "2349": "morale", "2350": "qu'", "2351": "on", "2352": "puisse", "2353": "en", "2354": "tirer", "2355": "hm", "2356": "hm", "2357": "et", "2358": "lorsque", "2359": "vous", "2360": "votez", "2361": "pour", "2362": "un", "2363": "d\u00e9put\u00e9", "2364": "qu'", "2365": "est", "2366": "-ce", "2367": "que", "2368": "vous", "2369": "attendez", "2370": "de", "2371": "lui", "2372": "?", "2373": "ben", "2374": "qu'", "2375": "il", "2376": "d\u00e9fende", "2377": "les", "2378": "int\u00e9r\u00eats", "2379": "de", "2380": "de", "2381": "la", "2382": "soci\u00e9t\u00e9", "2383": "dans", "2384": "l'", "2385": "optique", "2386": "euh", "2387": "politique", "2388": "euh", "2389": "qu'", "2390": "on", "2391": "a", "2392": "soi-m\u00eame", "2393": "hm", "2394": "hm", "2395": "et", "2396": "dans", "2397": "les", "2398": "\u00e9lections", "2399": "nationales", "2400": "pourquoi", "2401": "est", "2402": "-ce", "2403": "qu'", "2404": "il", "2405": "y", "2406": "a", "2407": "deux", "2408": "tours", "2409": "?", "2410": "est", "2411": "-ce", "2412": "qu'", "2413": "il", "2414": "y", "2415": "a", "2416": "?", "2417": "pourquoi", "2418": "est", "2419": "-ce", "2420": "qu'", "2421": "il", "2422": "y", "2423": "a", "2424": "deux", "2425": "tours", "2426": "?", "2427": "je", "2428": "comprends", "2429": "pas", "2430": "je", "2431": "crois", "2432": "qu'", "2433": "il", "2434": "y", "2435": "a", "2436": "deux", "2437": "tours", "2438": "en", "2439": "France", "2440": "deux", "2441": "y", "2442": "a", "2443": "deux", "2444": "tours", "2445": "oui", "2446": "?", "2447": "ben", "2448": "y", "2449": "a", "2450": "deux", "2451": "tours", "2452": "si", "2453": "y", "2454": "a", "2455": "ballotage", "2456": "et", "2457": "est", "2458": "-ce", "2459": "que", "2460": "vous", "2461": "pouvez", "2462": "expliquer", "2463": "ce", "2464": "que", "2465": "c'", "2466": "est", "2467": "euh", "2468": "le", "2469": "ballotage", "2470": "c'", "2471": "est", "2472": "?", "2473": "eh", "2474": "bien", "2475": "oui", "2476": "c'", "2477": "est", "2478": "quand", "2479": "un", "2480": "des", "2481": "candidats", "2482": "n'", "2483": "a-", "2484": "n'", "2485": "arrive", "2486": "pas", "2487": "\u00e0", "2488": "la", "2489": "majorit\u00e9", "2490": "absolue", "2491": "c'est-\u00e0-dire", "2492": "cinquante", "2493": "pour", "2494": "cent", "2495": "hm", "2496": "hm", "2497": "et", "2498": "ensuite", "2499": "il", "2500": "y", "2501": "a", "2502": "enfin", "2503": "\u00e7a", "2504": "c'", "2505": "est", "2506": "au", "2507": "premier", "2508": "tour", "2509": "y", "2510": "a", "2511": "y", "2512": "a", "2513": "d\u00e9sistement", "2514": "euh", "2515": "des", "2516": "candidats", "2517": "les", "2518": "moins", "2519": "bien", "2520": "plac\u00e9s", "2521": "hm", "2522": "hm", "2523": "et", "2524": "au", "2525": "deuxi\u00e8me", "2526": "tour", "2527": "il", "2528": "faut", "2529": "que", "2530": "les", "2531": "candidats", "2532": "aient", "2533": "la", "2534": "majorit\u00e9", "2535": "absolue", "2536": "hm", "2537": "hm", "2538": "s'", "2539": "il", "2540": "l'", "2541": "a", "2542": "pas", "2543": "y", "2544": "a", "2545": "un", "2546": "troisi\u00e8me", "2547": "tour", "2548": "y", "2549": "a", "2550": "un", "2551": "troisi\u00e8me", "2552": "tour", "2553": "?", "2554": "ah", "2555": "oui", "2556": "ah", "2557": "bon", "2558": "?", "2559": "et", "2560": "enfin", "2561": "si", "2562": "par", "2563": "exemple", "2564": "euh", "2565": "y", "2566": "a", "2567": "un", "2568": "deux-", "2569": "un", "2570": "deuxi\u00e8me", "2571": "tour", "2572": "comment", "2573": "est", "2574": "-ce", "2575": "qu'", "2576": "on", "2577": "d\u00e9cide", "2578": "son", "2579": "vote", "2580": "de", "2581": "la", "2582": "seconde", "2583": "fois", "2584": "?", "2585": "si", "2586": "mettons", "2587": "qu'", "2588": "on", "2589": "a", "2590": "pardon", "2591": "vot\u00e9", "2592": "pour", "2593": "quelqu'un", "2594": "qui", "2595": "qui", "2596": "s'", "2597": "est", "2598": "d\u00e9sist\u00e9", "2599": "?", "2600": "oui", "2601": "oui", "2602": "ben", "2603": "je", "2604": "crois", "2605": "que", "2606": "c'", "2607": "est", "2608": "la", "2609": "m\u00eame", "2610": "chose", "2611": "on", "2612": "se", "2613": "reporte", "2614": "sur", "2615": "le", "2616": "le", "2617": "candidat", "2618": "qui", "2619": "semble", "2620": "euh", "2621": "avoir", "2622": "le", "2623": "programme", "2624": "qui", "2625": "se", "2626": "rapproche", "2627": "le", "2628": "plus", "2629": "de", "2630": "de", "2631": "votre", "2632": "opinion", "2633": "hm", "2634": "hm", "2635": "et", "2636": "quelle", "2637": "est", "2638": "la", "2639": "diff\u00e9rence", "2640": "pensez-", "2641": "vous", "2642": "entre", "2643": "la", "2644": "droite", "2645": "et", "2646": "la", "2647": "gauche", "2648": "?", "2649": "oh", "2650": "disons", "2651": "que", "2652": "la", "2653": "droite", "2654": "est", "2655": "s\u00fbrement", "2656": "plus", "2657": "capitaliste", "2658": "que", "2659": "la", "2660": "gauche", "2661": "hm", "2662": "hm", "2663": "et", "2664": "vous", "2665": "croyez", "2666": "que", "2667": "y", "2668": "a", "2669": "une", "2670": "que", "2671": "la", "2672": "diff\u00e9rence", "2673": "existe", "2674": "euh", "2675": "r\u00e9ellement", "2676": "et", "2677": "en", "2678": "France", "2679": "?", "2680": "elle", "2681": "existe", "2682": "de", "2683": "moins", "2684": "en", "2685": "moins", "2686": "et", "2687": "elle", "2688": "existera", "2689": "de", "2690": "moins", "2691": "en", "2692": "moins", "2693": "hm", "2694": "hm", "2695": "et", "2696": "est", "2697": "-ce", "2698": "que", "2699": "les", "2700": "diff\u00e9rences", "2701": "entre", "2702": "les", "2703": "classes", "2704": "sociales", "2705": "sont", "2706": "tr\u00e8s", "2707": "marqu\u00e9es", "2708": "\u00e0", "2709": "Orl\u00e9ans", "2710": "?", "2711": "tr\u00e8s", "2712": "marqu\u00e9es", "2713": "non", "2714": "y", "2715": "a", "2716": "une", "2717": "euh", "2718": "une", "2719": "vieille", "2720": "bourgeoisie", "2721": "disons", "2722": "qui", "2723": "est", "2724": "mais", "2725": "enfin", "2726": "c'", "2727": "est", "2728": "pas", "2729": "euh", "2730": "elle", "2731": "n'", "2732": "a", "2733": "rien", "2734": "d'", "2735": "une", "2736": "classe", "2737": "dirigeante", "2738": "et", "2739": "elle", "2740": "a", "2741": "tout", "2742": "pris", "2743": "hein", "2744": "?", "2745": "c'", "2746": "est", "2747": "hm", "2748": "hm", "2749": "non", "2750": "\u00e0", "2751": "mon", "2752": "avis", "2753": "c'", "2754": "est", "2755": "pas", "2756": "tr\u00e8s", "2757": "marqu\u00e9", "2758": "non", "2759": "et", "2760": "est", "2761": "-ce", "2762": "que", "2763": "vous", "2764": "croyez", "2765": "qu'", "2766": "on", "2767": "peut", "2768": "reconna\u00eetre", "2769": "un", "2770": "membre", "2771": "de", "2772": "la", "2773": "vieille", "2774": "bourgeoisie", "2775": "?", "2776": "non", "2777": "non", "2778": "?", "2779": "non"}