{"1": {"CONTENT": ["SOS", "AMITIE", "BELFORT-MONTBELIARD"], "LEFT_CONTEXT": ["<start>"], "RIGHT_CONTEXT": ["24", "h", "sur", "24", ",", "t\u00e9l.", "03.81.98.35.35", ".", "<end>"], "START": "0", "END": "2", "SPAN_ID": "0-2"}, "2": {"CONTENT": ["MONTBELIARD", "COLISEE"], "LEFT_CONTEXT": ["<start>"], "RIGHT_CONTEXT": ["Tarif", "r\u00e9duit", "\u00e0", "17", "h", "14", "h", ",", "17", "h"], "START": "11", "END": "12", "SPAN_ID": "11-12"}, "3": {"CONTENT": ["Tarif", "r\u00e9duit"], "LEFT_CONTEXT": ["<start>", "MONTBELIARD", "COLISEE"], "RIGHT_CONTEXT": ["\u00e0", "17", "h", "14", "h", ",", "17", "h", "15", ","], "START": "13", "END": "14", "SPAN_ID": "13-14"}, "4": {"CONTENT": ["20", "h", "30"], "LEFT_CONTEXT": ["\u00e0", "17", "h", "14", "h", ",", "17", "h", "15", ","], "RIGHT_CONTEXT": [":", "\u00ab", "Le", "seigneur", "des", "anneaux", ":", "les", "deux", "tours"], "START": "25", "END": "27", "SPAN_ID": "25-27"}, "5": {"CONTENT": ["\u00ab", "Le", "seigneur", "des", "anneaux"], "LEFT_CONTEXT": ["h", ",", "17", "h", "15", ",", "20", "h", "30", ":"], "RIGHT_CONTEXT": [":", "les", "deux", "tours", "\u00bb", "(", "grand", "Colis\u00e9e", ",", "son"], "START": "29", "END": "33", "SPAN_ID": "29-33"}, "6": {"CONTENT": ["les", "deux", "tours", "\u00bb", "(", "grand", "Colis\u00e9e"], "LEFT_CONTEXT": ["20", "h", "30", ":", "\u00ab", "Le", "seigneur", "des", "anneaux", ":"], "RIGHT_CONTEXT": [",", "son", "DTS", ")", "14", "h", ",", "17", "h", ","], "START": "35", "END": "41", "SPAN_ID": "35-41"}, "7": {"CONTENT": ["son", "DTS"], "LEFT_CONTEXT": ["anneaux", ":", "les", "deux", "tours", "\u00bb", "(", "grand", "Colis\u00e9e", ","], "RIGHT_CONTEXT": [")", "14", "h", ",", "17", "h", ",", "20", "h", "15"], "START": "43", "END": "44", "SPAN_ID": "43-44"}, "8": {"CONTENT": ["17", "h", ",", "20", "h", "15"], "LEFT_CONTEXT": ["(", "grand", "Colis\u00e9e", ",", "son", "DTS", ")", "14", "h", ","], "RIGHT_CONTEXT": [":", "\u00ab", "Harry", "Potter", "et", "la", "chambre", "des", "secrets", "\u00bb"], "START": "49", "END": "54", "SPAN_ID": "49-54"}, "9": {"CONTENT": ["Harry", "Potter", "et", "la", "chambre", "des", "secrets"], "LEFT_CONTEXT": ["h", ",", "17", "h", ",", "20", "h", "15", ":", "\u00ab"], "RIGHT_CONTEXT": ["\u00bb", "(", "\u00e9cran", "panoramique", ",", "son", "dolby", "st\u00e9r\u00e9o", ")", "14"], "START": "57", "END": "63", "SPAN_ID": "57-63"}, "10": {"CONTENT": ["son", "dolby", "st\u00e9r\u00e9o"], "LEFT_CONTEXT": ["et", "la", "chambre", "des", "secrets", "\u00bb", "(", "\u00e9cran", "panoramique", ","], "RIGHT_CONTEXT": [")", "14", "h", "15", ",", "17", "h", ",", "20", "h"], "START": "69", "END": "71", "SPAN_ID": "69-71"}, "11": {"CONTENT": ["17", "h", ","], "LEFT_CONTEXT": ["panoramique", ",", "son", "dolby", "st\u00e9r\u00e9o", ")", "14", "h", "15", ","], "RIGHT_CONTEXT": ["20", "h", "15", ":", "\u00ab", "Spy", "kids", "2", "\u00bb", "14"], "START": "77", "END": "79", "SPAN_ID": "77-79"}, "12": {"CONTENT": ["20", "h", "15"], "LEFT_CONTEXT": ["dolby", "st\u00e9r\u00e9o", ")", "14", "h", "15", ",", "17", "h", ","], "RIGHT_CONTEXT": [":", "\u00ab", "Spy", "kids", "2", "\u00bb", "14", "h", "15", ",", "17"], "START": "80", "END": "82", "SPAN_ID": "80-82"}, "13": {"CONTENT": ["\u00ab", "Spy", "kids"], "LEFT_CONTEXT": ["h", "15", ",", "17", "h", ",", "20", "h", "15", ":"], "RIGHT_CONTEXT": ["2", "\u00bb", "14", "h", "15", ",", "17", "h", ",", "20", "h"], "START": "84", "END": "86", "SPAN_ID": "84-86"}, "14": {"CONTENT": ["14", "h", "15"], "LEFT_CONTEXT": [",", "20", "h", "15", ":", "\u00ab", "Spy", "kids", "2", "\u00bb"], "RIGHT_CONTEXT": [",", "17", "h", ",", "20", "h", "15", ":", "\u00ab", "Le", "vaisseau"], "START": "89", "END": "91", "SPAN_ID": "89-91"}, "15": {"CONTENT": ["17", "h", ",", "20", "h", "15"], "LEFT_CONTEXT": [":", "\u00ab", "Spy", "kids", "2", "\u00bb", "14", "h", "15", ","], "RIGHT_CONTEXT": [":", "\u00ab", "Le", "vaisseau", "de", "l'", "angoisse", "\u00bb", "PARVIS", "Tarif", "r\u00e9duit"], "START": "93", "END": "98", "SPAN_ID": "93-98"}, "16": {"CONTENT": ["\u00ab", "Le", "vaisseau", "de", "l'", "angoisse"], "LEFT_CONTEXT": ["h", "15", ",", "17", "h", ",", "20", "h", "15", ":"], "RIGHT_CONTEXT": ["\u00bb", "PARVIS", "Tarif", "r\u00e9duit", "\u00e0", "17", "h", ".", "<end>"], "START": "100", "END": "105", "SPAN_ID": "100-105"}, "17": {"CONTENT": ["l'", "angoisse", "\u00bb", "PARVIS"], "LEFT_CONTEXT": ["h", ",", "20", "h", "15", ":", "\u00ab", "Le", "vaisseau", "de"], "RIGHT_CONTEXT": ["Tarif", "r\u00e9duit", "\u00e0", "17", "h", ".", "<end>"], "START": "104", "END": "107", "SPAN_ID": "104-107"}, "18": {"CONTENT": ["Tarif", "r\u00e9duit"], "LEFT_CONTEXT": ["15", ":", "\u00ab", "Le", "vaisseau", "de", "l'", "angoisse", "\u00bb", "PARVIS"], "RIGHT_CONTEXT": ["\u00e0", "17", "h", ".", "<end>"], "START": "108", "END": "109", "SPAN_ID": "108-109"}, "19": {"CONTENT": ["17", "h", "."], "LEFT_CONTEXT": ["Le", "vaisseau", "de", "l'", "angoisse", "\u00bb", "PARVIS", "Tarif", "r\u00e9duit", "\u00e0"], "RIGHT_CONTEXT": ["<end>"], "START": "111", "END": "113", "SPAN_ID": "111-113"}, "20": {"CONTENT": ["14", "h", "15"], "LEFT_CONTEXT": ["<start>"], "RIGHT_CONTEXT": [",", "17", "h", ":", "\u00ab", "La", "plan\u00e8te", "au", "tr\u00e9sor", "\u00bb"], "START": "114", "END": "116", "SPAN_ID": "114-116"}, "21": {"CONTENT": ["17", "h"], "LEFT_CONTEXT": ["<start>", "14", "h", "15", ","], "RIGHT_CONTEXT": [":", "\u00ab", "La", "plan\u00e8te", "au", "tr\u00e9sor", "\u00bb", "14", "h", "15"], "START": "118", "END": "119", "SPAN_ID": "118-119"}, "22": {"CONTENT": ["\u00ab", "La", "plan\u00e8te", "au", "tr\u00e9sor"], "LEFT_CONTEXT": ["<start>", "14", "h", "15", ",", "17", "h", ":"], "RIGHT_CONTEXT": ["\u00bb", "14", "h", "15", ",", "17", "h", ",", "20", "h"], "START": "121", "END": "125", "SPAN_ID": "121-125"}, "23": {"CONTENT": ["14", "h", "15"], "LEFT_CONTEXT": [",", "17", "h", ":", "\u00ab", "La", "plan\u00e8te", "au", "tr\u00e9sor", "\u00bb"], "RIGHT_CONTEXT": [",", "17", "h", ",", "20", "h", "15", ":", "\u00ab", "Le"], "START": "127", "END": "129", "SPAN_ID": "127-129"}, "24": {"CONTENT": ["17", "h", ",", "20", "h", "15"], "LEFT_CONTEXT": ["\u00ab", "La", "plan\u00e8te", "au", "tr\u00e9sor", "\u00bb", "14", "h", "15", ","], "RIGHT_CONTEXT": [":", "\u00ab", "Le", "smoking", "\u00bb", "20", "h", "15", ":", "\u00ab"], "START": "131", "END": "136", "SPAN_ID": "131-136"}, "25": {"CONTENT": ["\u00ab", "Le", "smoking"], "LEFT_CONTEXT": ["h", "15", ",", "17", "h", ",", "20", "h", "15", ":"], "RIGHT_CONTEXT": ["\u00bb", "20", "h", "15", ":", "\u00ab", "Meurs", "un", "autre", "jour"], "START": "138", "END": "140", "SPAN_ID": "138-140"}, "26": {"CONTENT": ["20", "h", "15"], "LEFT_CONTEXT": ["h", ",", "20", "h", "15", ":", "\u00ab", "Le", "smoking", "\u00bb"], "RIGHT_CONTEXT": [":", "\u00ab", "Meurs", "un", "autre", "jour", "\u00bb", "14", "h", "15"], "START": "142", "END": "144", "SPAN_ID": "142-144"}, "27": {"CONTENT": ["un", "autre", "jour"], "LEFT_CONTEXT": ["\u00ab", "Le", "smoking", "\u00bb", "20", "h", "15", ":", "\u00ab", "Meurs"], "RIGHT_CONTEXT": ["\u00bb", "14", "h", "15", ",", "17", ",", "20", "h", "15"], "START": "148", "END": "150", "SPAN_ID": "148-150"}, "28": {"CONTENT": ["20", "h", "15"], "LEFT_CONTEXT": ["un", "autre", "jour", "\u00bb", "14", "h", "15", ",", "17", ","], "RIGHT_CONTEXT": [":", "\u00ab", "Le", "papillon", "\u00bb", "14", "h", "15", ",", "17"], "START": "158", "END": "160", "SPAN_ID": "158-160"}, "29": {"CONTENT": ["\u00ab", "Le", "papillon"], "LEFT_CONTEXT": ["14", "h", "15", ",", "17", ",", "20", "h", "15", ":"], "RIGHT_CONTEXT": ["\u00bb", "14", "h", "15", ",", "17", "h", ",", "20", "h"], "START": "162", "END": "164", "SPAN_ID": "162-164"}, "30": {"CONTENT": ["14", "h", "15"], "LEFT_CONTEXT": ["17", ",", "20", "h", "15", ":", "\u00ab", "Le", "papillon", "\u00bb"], "RIGHT_CONTEXT": [",", "17", "h", ",", "20", "h", "15", ":", "\u00ab", "Le"], "START": "166", "END": "168", "SPAN_ID": "166-168"}, "31": {"CONTENT": ["17", "h", ",", "20", "h", "15"], "LEFT_CONTEXT": ["15", ":", "\u00ab", "Le", "papillon", "\u00bb", "14", "h", "15", ","], "RIGHT_CONTEXT": [":", "\u00ab", "Le", "gourou", "et", "les", "femmes", "\u00bb", "AUDINCOURT", "LUMINA"], "START": "170", "END": "175", "SPAN_ID": "170-175"}, "32": {"CONTENT": ["\u00ab", "Le", "gourou", "et", "les", "femmes"], "LEFT_CONTEXT": ["h", "15", ",", "17", "h", ",", "20", "h", "15", ":"], "RIGHT_CONTEXT": ["\u00bb", "AUDINCOURT", "LUMINA", "Tarif", "r\u00e9duit", "\u00e0", "17", "h", "13", "h"], "START": "177", "END": "182", "SPAN_ID": "177-182"}, "33": {"CONTENT": ["les", "femmes", "\u00bb", "AUDINCOURT"], "LEFT_CONTEXT": ["h", ",", "20", "h", "15", ":", "\u00ab", "Le", "gourou", "et"], "RIGHT_CONTEXT": ["LUMINA", "Tarif", "r\u00e9duit", "\u00e0", "17", "h", "13", "h", "30", ","], "START": "181", "END": "184", "SPAN_ID": "181-184"}, "34": {"CONTENT": ["AUDINCOURT", "LUMINA"], "LEFT_CONTEXT": ["h", "15", ":", "\u00ab", "Le", "gourou", "et", "les", "femmes", "\u00bb"], "RIGHT_CONTEXT": ["Tarif", "r\u00e9duit", "\u00e0", "17", "h", "13", "h", "30", ",", "17"], "START": "184", "END": "185", "SPAN_ID": "184-185"}, "35": {"CONTENT": ["Tarif", "r\u00e9duit"], "LEFT_CONTEXT": [":", "\u00ab", "Le", "gourou", "et", "les", "femmes", "\u00bb", "AUDINCOURT", "LUMINA"], "RIGHT_CONTEXT": ["\u00e0", "17", "h", "13", "h", "30", ",", "17", "h", ","], "START": "186", "END": "187", "SPAN_ID": "186-187"}, "36": {"CONTENT": ["17", "h"], "LEFT_CONTEXT": ["gourou", "et", "les", "femmes", "\u00bb", "AUDINCOURT", "LUMINA", "Tarif", "r\u00e9duit", "\u00e0"], "RIGHT_CONTEXT": ["13", "h", "30", ",", "17", "h", ",", "20", "h", "15"], "START": "189", "END": "190", "SPAN_ID": "189-190"}, "37": {"CONTENT": ["13", "h", "30"], "LEFT_CONTEXT": ["les", "femmes", "\u00bb", "AUDINCOURT", "LUMINA", "Tarif", "r\u00e9duit", "\u00e0", "17", "h"], "RIGHT_CONTEXT": [",", "17", "h", ",", "20", "h", "15", ":", "\u00ab", "Le"], "START": "191", "END": "193", "SPAN_ID": "191-193"}, "38": {"CONTENT": ["17", "h", ",", "20", "h", "15"], "LEFT_CONTEXT": ["LUMINA", "Tarif", "r\u00e9duit", "\u00e0", "17", "h", "13", "h", "30", ","], "RIGHT_CONTEXT": [":", "\u00ab", "Le", "seigneur", "des", "anneaux", ":", "les", "deux", "tours"], "START": "195", "END": "200", "SPAN_ID": "195-200"}, "39": {"CONTENT": ["\u00ab", "Le", "seigneur", "des", "anneaux"], "LEFT_CONTEXT": ["h", "30", ",", "17", "h", ",", "20", "h", "15", ":"], "RIGHT_CONTEXT": [":", "les", "deux", "tours", "\u00bb", "14", "h", ",", "17", "h"], "START": "202", "END": "206", "SPAN_ID": "202-206"}, "40": {"CONTENT": ["les", "deux", "tours"], "LEFT_CONTEXT": ["20", "h", "15", ":", "\u00ab", "Le", "seigneur", "des", "anneaux", ":"], "RIGHT_CONTEXT": ["\u00bb", "14", "h", ",", "17", "h", ",", "20", "h", "15"], "START": "208", "END": "210", "SPAN_ID": "208-210"}, "41": {"CONTENT": ["17", "h", ",", "20", "h", "15"], "LEFT_CONTEXT": ["des", "anneaux", ":", "les", "deux", "tours", "\u00bb", "14", "h", ","], "RIGHT_CONTEXT": [":", "\u00ab", "Harry", "Potter", "et", "la", "chambre", "des", "secrets", "\u00bb"], "START": "215", "END": "220", "SPAN_ID": "215-220"}, "42": {"CONTENT": ["Harry", "Potter", "et", "la", "chambre", "des", "secrets"], "LEFT_CONTEXT": ["h", ",", "17", "h", ",", "20", "h", "15", ":", "\u00ab"], "RIGHT_CONTEXT": ["\u00bb", "23", "h", ":", "\u00ab", "Le", "smoking", "\u00bb", "14", "h"], "START": "223", "END": "229", "SPAN_ID": "223-229"}, "43": {"CONTENT": ["23", "h"], "LEFT_CONTEXT": [":", "\u00ab", "Harry", "Potter", "et", "la", "chambre", "des", "secrets", "\u00bb"], "RIGHT_CONTEXT": [":", "\u00ab", "Le", "smoking", "\u00bb", "14", "h", ",", "20", "h"], "START": "231", "END": "232", "SPAN_ID": "231-232"}, "44": {"CONTENT": ["\u00ab", "Le", "smoking"], "LEFT_CONTEXT": ["Potter", "et", "la", "chambre", "des", "secrets", "\u00bb", "23", "h", ":"], "RIGHT_CONTEXT": ["\u00bb", "14", "h", ",", "20", "h", "15", ",", "23", "h"], "START": "234", "END": "236", "SPAN_ID": "234-236"}, "45": {"CONTENT": ["20", "h", "15"], "LEFT_CONTEXT": ["23", "h", ":", "\u00ab", "Le", "smoking", "\u00bb", "14", "h", ","], "RIGHT_CONTEXT": [",", "23", "h", "15", ":", "\u00ab", "Le", "vaisseau", "de", "l'"], "START": "241", "END": "243", "SPAN_ID": "241-243"}, "46": {"CONTENT": ["23", "h", "15"], "LEFT_CONTEXT": ["Le", "smoking", "\u00bb", "14", "h", ",", "20", "h", "15", ","], "RIGHT_CONTEXT": [":", "\u00ab", "Le", "vaisseau", "de", "l'", "angoisse", "\u00bb", "17", "h"], "START": "245", "END": "247", "SPAN_ID": "245-247"}, "47": {"CONTENT": ["\u00ab", "Le", "vaisseau", "de", "l'", "angoisse"], "LEFT_CONTEXT": ["h", ",", "20", "h", "15", ",", "23", "h", "15", ":"], "RIGHT_CONTEXT": ["\u00bb", "17", "h", "45", ":", "\u00ab", "Hyper", "No\u00ebl", "\u00bb", "16"], "START": "249", "END": "254", "SPAN_ID": "249-254"}, "48": {"CONTENT": ["17", "h", "45"], "LEFT_CONTEXT": ["h", "15", ":", "\u00ab", "Le", "vaisseau", "de", "l'", "angoisse", "\u00bb"], "RIGHT_CONTEXT": [":", "\u00ab", "Hyper", "No\u00ebl", "\u00bb", "16", "h", ",", "22", "h"], "START": "256", "END": "258", "SPAN_ID": "256-258"}, "49": {"CONTENT": ["\u00ab", "Hyper", "No\u00ebl"], "LEFT_CONTEXT": ["Le", "vaisseau", "de", "l'", "angoisse", "\u00bb", "17", "h", "45", ":"], "RIGHT_CONTEXT": ["\u00bb", "16", "h", ",", "22", "h", "30", ":", "\u00ab", "Le"], "START": "260", "END": "262", "SPAN_ID": "260-262"}, "50": {"CONTENT": ["16", "h", ",", "22", "h", "30"], "LEFT_CONTEXT": ["angoisse", "\u00bb", "17", "h", "45", ":", "\u00ab", "Hyper", "No\u00ebl", "\u00bb"], "RIGHT_CONTEXT": [":", "\u00ab", "Le", "gourou", "et", "les", "femmes", "\u00bb", "16", "h"], "START": "264", "END": "269", "SPAN_ID": "264-269"}, "51": {"CONTENT": ["\u00ab", "Le", "gourou", "et", "les", "femmes"], "LEFT_CONTEXT": ["Hyper", "No\u00ebl", "\u00bb", "16", "h", ",", "22", "h", "30", ":"], "RIGHT_CONTEXT": ["\u00bb", "16", "h", ":", "\u00ab", "La", "plan\u00e8te", "au", "tr\u00e9sor", "\u00bb"], "START": "271", "END": "276", "SPAN_ID": "271-276"}, "52": {"CONTENT": ["les", "femmes", "\u00bb"], "LEFT_CONTEXT": ["h", ",", "22", "h", "30", ":", "\u00ab", "Le", "gourou", "et"], "RIGHT_CONTEXT": ["16", "h", ":", "\u00ab", "La", "plan\u00e8te", "au", "tr\u00e9sor", "\u00bb", "17"], "START": "275", "END": "277", "SPAN_ID": "275-277"}, "53": {"CONTENT": ["16", "h"], "LEFT_CONTEXT": ["h", "30", ":", "\u00ab", "Le", "gourou", "et", "les", "femmes", "\u00bb"], "RIGHT_CONTEXT": [":", "\u00ab", "La", "plan\u00e8te", "au", "tr\u00e9sor", "\u00bb", "17", "h", "45"], "START": "278", "END": "279", "SPAN_ID": "278-279"}, "54": {"CONTENT": ["\u00ab", "La", "plan\u00e8te", "au", "tr\u00e9sor"], "LEFT_CONTEXT": ["\u00ab", "Le", "gourou", "et", "les", "femmes", "\u00bb", "16", "h", ":"], "RIGHT_CONTEXT": ["\u00bb", "17", "h", "45", ",", "20", "h", "15", ":", "\u00ab"], "START": "281", "END": "285", "SPAN_ID": "281-285"}, "55": {"CONTENT": ["17", "h", "45", ",", "20", "h", "15"], "LEFT_CONTEXT": ["\u00bb", "16", "h", ":", "\u00ab", "La", "plan\u00e8te", "au", "tr\u00e9sor", "\u00bb"], "RIGHT_CONTEXT": [":", "\u00ab", "Le", "papillon", "\u00bb", "14", "h", ":", "\u00ab", "Spy"], "START": "287", "END": "293", "SPAN_ID": "287-293"}, "56": {"CONTENT": ["\u00ab", "Le", "papillon"], "LEFT_CONTEXT": ["tr\u00e9sor", "\u00bb", "17", "h", "45", ",", "20", "h", "15", ":"], "RIGHT_CONTEXT": ["\u00bb", "14", "h", ":", "\u00ab", "Spy", "kids", "2", "\u00bb", "22"], "START": "295", "END": "297", "SPAN_ID": "295-297"}, "57": {"CONTENT": ["14", "h"], "LEFT_CONTEXT": ["45", ",", "20", "h", "15", ":", "\u00ab", "Le", "papillon", "\u00bb"], "RIGHT_CONTEXT": [":", "\u00ab", "Spy", "kids", "2", "\u00bb", "22", "h", "30", ":"], "START": "299", "END": "300", "SPAN_ID": "299-300"}, "58": {"CONTENT": ["\u00ab", "Spy", "kids", "2"], "LEFT_CONTEXT": ["h", "15", ":", "\u00ab", "Le", "papillon", "\u00bb", "14", "h", ":"], "RIGHT_CONTEXT": ["\u00bb", "22", "h", "30", ":", "\u00ab", "007", ",", "Meurs", "un"], "START": "302", "END": "305", "SPAN_ID": "302-305"}, "59": {"CONTENT": ["22", "h", "30"], "LEFT_CONTEXT": ["papillon", "\u00bb", "14", "h", ":", "\u00ab", "Spy", "kids", "2", "\u00bb"], "RIGHT_CONTEXT": [":", "\u00ab", "007", ",", "Meurs", "un", "autre", "jour", "\u00bb", "BELFORT"], "START": "307", "END": "309", "SPAN_ID": "307-309"}, "60": {"CONTENT": ["\u00ab", "007"], "LEFT_CONTEXT": [":", "\u00ab", "Spy", "kids", "2", "\u00bb", "22", "h", "30", ":"], "RIGHT_CONTEXT": [",", "Meurs", "un", "autre", "jour", "\u00bb", "BELFORT", "CINEMA", "DES", "QUAIS"], "START": "311", "END": "312", "SPAN_ID": "311-312"}, "61": {"CONTENT": ["un", "autre", "jour"], "LEFT_CONTEXT": ["2", "\u00bb", "22", "h", "30", ":", "\u00ab", "007", ",", "Meurs"], "RIGHT_CONTEXT": ["\u00bb", "BELFORT", "CINEMA", "DES", "QUAIS", "13", "h", "40", ",", "15"], "START": "315", "END": "317", "SPAN_ID": "315-317"}, "62": {"CONTENT": ["BELFORT"], "LEFT_CONTEXT": ["30", ":", "\u00ab", "007", ",", "Meurs", "un", "autre", "jour", "\u00bb"], "RIGHT_CONTEXT": ["CINEMA", "DES", "QUAIS", "13", "h", "40", ",", "15", "h", "50"], "START": "319", "END": "319", "SPAN_ID": "319-319"}, "63": {"CONTENT": ["CINEMA", "DES", "QUAIS"], "LEFT_CONTEXT": [":", "\u00ab", "007", ",", "Meurs", "un", "autre", "jour", "\u00bb", "BELFORT"], "RIGHT_CONTEXT": ["13", "h", "40", ",", "15", "h", "50", ",", "18", "h"], "START": "320", "END": "322", "SPAN_ID": "320-322"}, "64": {"CONTENT": ["15", "h", "50"], "LEFT_CONTEXT": ["jour", "\u00bb", "BELFORT", "CINEMA", "DES", "QUAIS", "13", "h", "40", ","], "RIGHT_CONTEXT": [",", "18", "h", ",", "20", "h", "10", ",", "22", "h"], "START": "327", "END": "329", "SPAN_ID": "327-329"}, "65": {"CONTENT": ["18", "h", ","], "LEFT_CONTEXT": ["DES", "QUAIS", "13", "h", "40", ",", "15", "h", "50", ","], "RIGHT_CONTEXT": ["20", "h", "10", ",", "22", "h", "20", ":", "\u00ab", "Spy"], "START": "331", "END": "333", "SPAN_ID": "331-333"}, "66": {"CONTENT": ["20", "h", "10"], "LEFT_CONTEXT": ["h", "40", ",", "15", "h", "50", ",", "18", "h", ","], "RIGHT_CONTEXT": [",", "22", "h", "20", ":", "\u00ab", "Spy", "kids", "2", "\u00bb"], "START": "334", "END": "336", "SPAN_ID": "334-336"}, "67": {"CONTENT": ["22", "h", "20"], "LEFT_CONTEXT": ["h", "50", ",", "18", "h", ",", "20", "h", "10", ","], "RIGHT_CONTEXT": [":", "\u00ab", "Spy", "kids", "2", "\u00bb", "14", "h", ",", "16"], "START": "338", "END": "340", "SPAN_ID": "338-340"}, "68": {"CONTENT": ["\u00ab", "Spy", "kids"], "LEFT_CONTEXT": ["h", ",", "20", "h", "10", ",", "22", "h", "20", ":"], "RIGHT_CONTEXT": ["2", "\u00bb", "14", "h", ",", "16", "h", ",", "18", "h"], "START": "342", "END": "344", "SPAN_ID": "342-344"}, "69": {"CONTENT": ["14", "h", ","], "LEFT_CONTEXT": [",", "22", "h", "20", ":", "\u00ab", "Spy", "kids", "2", "\u00bb"], "RIGHT_CONTEXT": ["16", "h", ",", "18", "h", ",", "20", "h", ",", "22"], "START": "347", "END": "349", "SPAN_ID": "347-349"}, "70": {"CONTENT": ["16", "h", ","], "LEFT_CONTEXT": ["20", ":", "\u00ab", "Spy", "kids", "2", "\u00bb", "14", "h", ","], "RIGHT_CONTEXT": ["18", "h", ",", "20", "h", ",", "22", "h", ":", "\u00ab"], "START": "350", "END": "352", "SPAN_ID": "350-352"}, "71": {"CONTENT": ["18", "h", ","], "LEFT_CONTEXT": ["Spy", "kids", "2", "\u00bb", "14", "h", ",", "16", "h", ","], "RIGHT_CONTEXT": ["20", "h", ",", "22", "h", ":", "\u00ab", "Le", "vaisseau", "de"], "START": "353", "END": "355", "SPAN_ID": "353-355"}, "72": {"CONTENT": ["20", "h", ",", "22", "h"], "LEFT_CONTEXT": ["\u00bb", "14", "h", ",", "16", "h", ",", "18", "h", ","], "RIGHT_CONTEXT": [":", "\u00ab", "Le", "vaisseau", "de", "l'", "angoisse", "\u00bb", "(", "int"], "START": "356", "END": "360", "SPAN_ID": "356-360"}, "73": {"CONTENT": ["\u00ab", "Le", "vaisseau", "de", "l'", "angoisse", "\u00bb", "(", "int", ".", "-", "12", "ans"], "LEFT_CONTEXT": [",", "18", "h", ",", "20", "h", ",", "22", "h", ":"], "RIGHT_CONTEXT": [")", "13", "h", "40", ",", "15", "h", "50", ",", "18"], "START": "362", "END": "374", "SPAN_ID": "362-374"}, "74": {"CONTENT": ["13", "h", "40", ","], "LEFT_CONTEXT": ["l'", "angoisse", "\u00bb", "(", "int", ".", "-", "12", "ans", ")"], "RIGHT_CONTEXT": ["15", "h", "50", ",", "18", "h", ",", "20", "h", "10"], "START": "376", "END": "379", "SPAN_ID": "376-379"}, "75": {"CONTENT": ["15", "h", "50"], "LEFT_CONTEXT": ["int", ".", "-", "12", "ans", ")", "13", "h", "40", ","], "RIGHT_CONTEXT": [",", "18", "h", ",", "20", "h", "10", ",", "22", "h"], "START": "380", "END": "382", "SPAN_ID": "380-382"}, "76": {"CONTENT": ["18", "h", ","], "LEFT_CONTEXT": ["ans", ")", "13", "h", "40", ",", "15", "h", "50", ","], "RIGHT_CONTEXT": ["20", "h", "10", ",", "22", "h", "20", ":", "\u00ab", "Un"], "START": "384", "END": "386", "SPAN_ID": "384-386"}, "77": {"CONTENT": ["20", "h", "10"], "LEFT_CONTEXT": ["h", "40", ",", "15", "h", "50", ",", "18", "h", ","], "RIGHT_CONTEXT": [",", "22", "h", "20", ":", "\u00ab", "Un", "couple", "\u00e9patant", "\u00bb"], "START": "387", "END": "389", "SPAN_ID": "387-389"}, "78": {"CONTENT": ["22", "h", "20"], "LEFT_CONTEXT": ["h", "50", ",", "18", "h", ",", "20", "h", "10", ","], "RIGHT_CONTEXT": [":", "\u00ab", "Un", "couple", "\u00e9patant", "\u00bb", "(", "VO", ")", "14"], "START": "391", "END": "393", "SPAN_ID": "391-393"}, "79": {"CONTENT": ["\u00ab", "Un", "couple", "\u00e9patant"], "LEFT_CONTEXT": ["h", ",", "20", "h", "10", ",", "22", "h", "20", ":"], "RIGHT_CONTEXT": ["\u00bb", "(", "VO", ")", "14", "h", ",", "16", "h", ","], "START": "395", "END": "398", "SPAN_ID": "395-398"}, "80": {"CONTENT": ["(", "VO"], "LEFT_CONTEXT": [",", "22", "h", "20", ":", "\u00ab", "Un", "couple", "\u00e9patant", "\u00bb"], "RIGHT_CONTEXT": [")", "14", "h", ",", "16", "h", ",", "18", "h", ","], "START": "400", "END": "401", "SPAN_ID": "400-401"}, "81": {"CONTENT": ["14", "h", ","], "LEFT_CONTEXT": ["20", ":", "\u00ab", "Un", "couple", "\u00e9patant", "\u00bb", "(", "VO", ")"], "RIGHT_CONTEXT": ["16", "h", ",", "18", "h", ",", "20", "h", ",", "22"], "START": "403", "END": "405", "SPAN_ID": "403-405"}, "82": {"CONTENT": ["16", "h", ","], "LEFT_CONTEXT": ["Un", "couple", "\u00e9patant", "\u00bb", "(", "VO", ")", "14", "h", ","], "RIGHT_CONTEXT": ["18", "h", ",", "20", "h", ",", "22", "h", ":", "\u00ab"], "START": "406", "END": "408", "SPAN_ID": "406-408"}, "83": {"CONTENT": ["18", "h"], "LEFT_CONTEXT": ["\u00bb", "(", "VO", ")", "14", "h", ",", "16", "h", ","], "RIGHT_CONTEXT": [",", "20", "h", ",", "22", "h", ":", "\u00ab", "Respiro", "\u00bb"], "START": "409", "END": "410", "SPAN_ID": "409-410"}, "84": {"CONTENT": ["20", "h", ","], "LEFT_CONTEXT": [")", "14", "h", ",", "16", "h", ",", "18", "h", ","], "RIGHT_CONTEXT": ["22", "h", ":", "\u00ab", "Respiro", "\u00bb", "20", "h", ",", "22"], "START": "412", "END": "414", "SPAN_ID": "412-414"}, "85": {"CONTENT": ["22", "h"], "LEFT_CONTEXT": [",", "16", "h", ",", "18", "h", ",", "20", "h", ","], "RIGHT_CONTEXT": [":", "\u00ab", "Respiro", "\u00bb", "20", "h", ",", "22", "h", ":"], "START": "415", "END": "416", "SPAN_ID": "415-416"}, "86": {"CONTENT": ["\u00ab", "Respiro"], "LEFT_CONTEXT": [",", "18", "h", ",", "20", "h", ",", "22", "h", ":"], "RIGHT_CONTEXT": ["\u00bb", "20", "h", ",", "22", "h", ":", "\u00ab", "Le", "gourou"], "START": "418", "END": "419", "SPAN_ID": "418-419"}, "87": {"CONTENT": ["20", "h", ",", "22", "h"], "LEFT_CONTEXT": [",", "20", "h", ",", "22", "h", ":", "\u00ab", "Respiro", "\u00bb"], "RIGHT_CONTEXT": [":", "\u00ab", "Le", "gourou", "et", "les", "femmes", "\u00bb", "13", "h"], "START": "421", "END": "425", "SPAN_ID": "421-425"}, "88": {"CONTENT": ["\u00ab", "Le", "gourou", "et", "les", "femmes"], "LEFT_CONTEXT": [":", "\u00ab", "Respiro", "\u00bb", "20", "h", ",", "22", "h", ":"], "RIGHT_CONTEXT": ["\u00bb", "13", "h", "50", ",", "14", "h", "30", ",", "17"], "START": "427", "END": "432", "SPAN_ID": "427-432"}, "89": {"CONTENT": ["13", "h", "50"], "LEFT_CONTEXT": ["22", "h", ":", "\u00ab", "Le", "gourou", "et", "les", "femmes", "\u00bb"], "RIGHT_CONTEXT": [",", "14", "h", "30", ",", "17", "h", "15", ",", "18"], "START": "434", "END": "436", "SPAN_ID": "434-436"}, "90": {"CONTENT": ["14", "h", "30", ","], "LEFT_CONTEXT": ["Le", "gourou", "et", "les", "femmes", "\u00bb", "13", "h", "50", ","], "RIGHT_CONTEXT": ["17", "h", "15", ",", "18", "h", ",", "20", "h", "45"], "START": "438", "END": "441", "SPAN_ID": "438-441"}, "91": {"CONTENT": ["17", "h", "15"], "LEFT_CONTEXT": ["femmes", "\u00bb", "13", "h", "50", ",", "14", "h", "30", ","], "RIGHT_CONTEXT": [",", "18", "h", ",", "20", "h", "45", ",", "21", "h"], "START": "442", "END": "444", "SPAN_ID": "442-444"}, "92": {"CONTENT": ["18", "h", ","], "LEFT_CONTEXT": ["50", ",", "14", "h", "30", ",", "17", "h", "15", ","], "RIGHT_CONTEXT": ["20", "h", "45", ",", "21", "h", "30", ":", "\u00ab", "Le"], "START": "446", "END": "448", "SPAN_ID": "446-448"}, "93": {"CONTENT": ["20", "h", "45"], "LEFT_CONTEXT": ["h", "30", ",", "17", "h", "15", ",", "18", "h", ","], "RIGHT_CONTEXT": [",", "21", "h", "30", ":", "\u00ab", "Le", "seigneur", "des", "anneaux"], "START": "449", "END": "451", "SPAN_ID": "449-451"}, "94": {"CONTENT": ["21", "h", "30"], "LEFT_CONTEXT": ["h", "15", ",", "18", "h", ",", "20", "h", "45", ","], "RIGHT_CONTEXT": [":", "\u00ab", "Le", "seigneur", "des", "anneaux", ":", "les", "deux", "tours"], "START": "453", "END": "455", "SPAN_ID": "453-455"}, "95": {"CONTENT": ["\u00ab", "Le", "seigneur", "des", "anneaux"], "LEFT_CONTEXT": ["h", ",", "20", "h", "45", ",", "21", "h", "30", ":"], "RIGHT_CONTEXT": [":", "les", "deux", "tours", "\u00bb", "14", "h", ",", "14", "h"], "START": "457", "END": "461", "SPAN_ID": "457-461"}, "96": {"CONTENT": ["les", "deux", "tours"], "LEFT_CONTEXT": ["21", "h", "30", ":", "\u00ab", "Le", "seigneur", "des", "anneaux", ":"], "RIGHT_CONTEXT": ["\u00bb", "14", "h", ",", "14", "h", "30", ",", "17", "h"], "START": "463", "END": "465", "SPAN_ID": "463-465"}, "97": {"CONTENT": ["14", "h", "30"], "LEFT_CONTEXT": ["des", "anneaux", ":", "les", "deux", "tours", "\u00bb", "14", "h", ","], "RIGHT_CONTEXT": [",", "17", "h", ",", "17", "h", "30", ",", "20", "h"], "START": "470", "END": "472", "SPAN_ID": "470-472"}, "98": {"CONTENT": ["17", "h", ","], "LEFT_CONTEXT": ["deux", "tours", "\u00bb", "14", "h", ",", "14", "h", "30", ","], "RIGHT_CONTEXT": ["17", "h", "30", ",", "20", "h", ",", "21", "h", ":"], "START": "474", "END": "476", "SPAN_ID": "474-476"}, "99": {"CONTENT": ["17", "h", "30", ","], "LEFT_CONTEXT": ["14", "h", ",", "14", "h", "30", ",", "17", "h", ","], "RIGHT_CONTEXT": ["20", "h", ",", "21", "h", ":", "\u00ab", "Harry", "Potter", "et"], "START": "477", "END": "480", "SPAN_ID": "477-480"}, "100": {"CONTENT": ["20", "h", ",", "21", "h"], "LEFT_CONTEXT": ["h", "30", ",", "17", "h", ",", "17", "h", "30", ","], "RIGHT_CONTEXT": [":", "\u00ab", "Harry", "Potter", "et", "la", "chambre", "des", "sorciers", "\u00bb"], "START": "481", "END": "485", "SPAN_ID": "481-485"}, "101": {"CONTENT": ["Harry", "Potter", "et", "la", "chambre", "des", "sorciers"], "LEFT_CONTEXT": ["h", "30", ",", "20", "h", ",", "21", "h", ":", "\u00ab"], "RIGHT_CONTEXT": ["\u00bb", "14", "h", ",", "17", "h", "30", ",", "20", "h"], "START": "488", "END": "494", "SPAN_ID": "488-494"}, "102": {"CONTENT": ["17", "h", "30", ","], "LEFT_CONTEXT": ["Potter", "et", "la", "chambre", "des", "sorciers", "\u00bb", "14", "h", ","], "RIGHT_CONTEXT": ["20", "h", "10", ",", "22", "h", "10", ":", "\u00ab", "Meurs"], "START": "499", "END": "502", "SPAN_ID": "499-502"}, "103": {"CONTENT": ["20", "h", "10"], "LEFT_CONTEXT": ["des", "sorciers", "\u00bb", "14", "h", ",", "17", "h", "30", ","], "RIGHT_CONTEXT": [",", "22", "h", "10", ":", "\u00ab", "Meurs", "un", "autre", "jour"], "START": "503", "END": "505", "SPAN_ID": "503-505"}, "104": {"CONTENT": ["22", "h", "10"], "LEFT_CONTEXT": ["h", ",", "17", "h", "30", ",", "20", "h", "10", ","], "RIGHT_CONTEXT": [":", "\u00ab", "Meurs", "un", "autre", "jour", "\u00bb", "14", "h", ","], "START": "507", "END": "509", "SPAN_ID": "507-509"}, "105": {"CONTENT": ["un", "autre", "jour"], "LEFT_CONTEXT": ["20", "h", "10", ",", "22", "h", "10", ":", "\u00ab", "Meurs"], "RIGHT_CONTEXT": ["\u00bb", "14", "h", ",", "16", "h", ",", "18", "h", ":"], "START": "513", "END": "515", "SPAN_ID": "513-515"}, "106": {"CONTENT": ["16", "h", ",", "18", "h"], "LEFT_CONTEXT": [":", "\u00ab", "Meurs", "un", "autre", "jour", "\u00bb", "14", "h", ","], "RIGHT_CONTEXT": [":", "\u00ab", "La", "plan\u00e8te", "au", "tr\u00e9sor", "\u00bb", "14", "h", ","], "START": "520", "END": "524", "SPAN_ID": "520-524"}, "107": {"CONTENT": ["\u00ab", "La", "plan\u00e8te", "au", "tr\u00e9sor"], "LEFT_CONTEXT": ["\u00bb", "14", "h", ",", "16", "h", ",", "18", "h", ":"], "RIGHT_CONTEXT": ["\u00bb", "14", "h", ",", "16", "h", ",", "18", "h", ","], "START": "526", "END": "530", "SPAN_ID": "526-530"}, "108": {"CONTENT": ["14", "h"], "LEFT_CONTEXT": [",", "18", "h", ":", "\u00ab", "La", "plan\u00e8te", "au", "tr\u00e9sor", "\u00bb"], "RIGHT_CONTEXT": [",", "16", "h", ",", "18", "h", ",", "20", "h", ":"], "START": "532", "END": "533", "SPAN_ID": "532-533"}, "109": {"CONTENT": ["16", "h"], "LEFT_CONTEXT": [":", "\u00ab", "La", "plan\u00e8te", "au", "tr\u00e9sor", "\u00bb", "14", "h", ","], "RIGHT_CONTEXT": [",", "18", "h", ",", "20", "h", ":", "\u00ab", "Le", "papillon"], "START": "535", "END": "536", "SPAN_ID": "535-536"}, "110": {"CONTENT": ["18", "h", ",", "20", "h"], "LEFT_CONTEXT": ["plan\u00e8te", "au", "tr\u00e9sor", "\u00bb", "14", "h", ",", "16", "h", ","], "RIGHT_CONTEXT": [":", "\u00ab", "Le", "papillon", "\u00bb", "20", "h", ",", "22", "h"], "START": "538", "END": "542", "SPAN_ID": "538-542"}, "111": {"CONTENT": ["\u00ab", "Le", "papillon"], "LEFT_CONTEXT": [",", "16", "h", ",", "18", "h", ",", "20", "h", ":"], "RIGHT_CONTEXT": ["\u00bb", "20", "h", ",", "22", "h", "10", ":", "\u00ab", "Le"], "START": "544", "END": "546", "SPAN_ID": "544-546"}, "112": {"CONTENT": ["20", "h", ",", "22", "h", "10"], "LEFT_CONTEXT": ["18", "h", ",", "20", "h", ":", "\u00ab", "Le", "papillon", "\u00bb"], "RIGHT_CONTEXT": [":", "\u00ab", "Le", "smoking", "\u00bb", "14", "h", ",", "16", "h"], "START": "548", "END": "553", "SPAN_ID": "548-553"}, "113": {"CONTENT": ["\u00ab", "Le", "smoking"], "LEFT_CONTEXT": ["Le", "papillon", "\u00bb", "20", "h", ",", "22", "h", "10", ":"], "RIGHT_CONTEXT": ["\u00bb", "14", "h", ",", "16", "h", ":", "\u00ab", "L'", "enfant"], "START": "555", "END": "557", "SPAN_ID": "555-557"}, "114": {"CONTENT": ["14", "h", ",", "16", "h"], "LEFT_CONTEXT": ["h", ",", "22", "h", "10", ":", "\u00ab", "Le", "smoking", "\u00bb"], "RIGHT_CONTEXT": [":", "\u00ab", "L'", "enfant", "qui", "voulait", "\u00eatre", "un", "ours", "\u00bb"], "START": "559", "END": "563", "SPAN_ID": "559-563"}, "115": {"CONTENT": ["L'", "enfant"], "LEFT_CONTEXT": ["Le", "smoking", "\u00bb", "14", "h", ",", "16", "h", ":", "\u00ab"], "RIGHT_CONTEXT": ["qui", "voulait", "\u00eatre", "un", "ours", "\u00bb", "18", "h", ",", "20"], "START": "566", "END": "567", "SPAN_ID": "566-567"}, "116": {"CONTENT": ["qui"], "LEFT_CONTEXT": ["\u00bb", "14", "h", ",", "16", "h", ":", "\u00ab", "L'", "enfant"], "RIGHT_CONTEXT": ["voulait", "\u00eatre", "un", "ours", "\u00bb", "18", "h", ",", "20", "h"], "START": "568", "END": "568", "SPAN_ID": "568-568"}, "117": {"CONTENT": ["un", "ours"], "LEFT_CONTEXT": [",", "16", "h", ":", "\u00ab", "L'", "enfant", "qui", "voulait", "\u00eatre"], "RIGHT_CONTEXT": ["\u00bb", "18", "h", ",", "20", "h", "10", ":", "\u00ab", "Mon"], "START": "571", "END": "572", "SPAN_ID": "571-572"}, "118": {"CONTENT": ["18", "h", ",", "20", "h", "10"], "LEFT_CONTEXT": [":", "\u00ab", "L'", "enfant", "qui", "voulait", "\u00eatre", "un", "ours", "\u00bb"], "RIGHT_CONTEXT": [":", "\u00ab", "Mon", "idole", "\u00bb", "17", "h", "50", ":", "\u00ab"], "START": "574", "END": "579", "SPAN_ID": "574-579"}, "119": {"CONTENT": ["\u00ab", "Mon", "idole"], "LEFT_CONTEXT": ["un", "ours", "\u00bb", "18", "h", ",", "20", "h", "10", ":"], "RIGHT_CONTEXT": ["\u00bb", "17", "h", "50", ":", "\u00ab", "Etre", "et", "avoir", "\u00bb"], "START": "581", "END": "583", "SPAN_ID": "581-583"}, "120": {"CONTENT": ["17", "h", "50"], "LEFT_CONTEXT": ["h", ",", "20", "h", "10", ":", "\u00ab", "Mon", "idole", "\u00bb"], "RIGHT_CONTEXT": [":", "\u00ab", "Etre", "et", "avoir", "\u00bb", "20", "h", ":", "\u00ab"], "START": "585", "END": "587", "SPAN_ID": "585-587"}, "121": {"CONTENT": ["20", "h"], "LEFT_CONTEXT": ["\u00bb", "17", "h", "50", ":", "\u00ab", "Etre", "et", "avoir", "\u00bb"], "RIGHT_CONTEXT": [":", "\u00ab", "Ah", "!", "si", "j'", "\u00e9tais", "riche", "\u00bb", "17"], "START": "594", "END": "595", "SPAN_ID": "594-595"}, "122": {"CONTENT": ["j'"], "LEFT_CONTEXT": ["et", "avoir", "\u00bb", "20", "h", ":", "\u00ab", "Ah", "!", "si"], "RIGHT_CONTEXT": ["\u00e9tais", "riche", "\u00bb", "17", "h", "50", ":", "\u00ab", "C'", "est"], "START": "601", "END": "601", "SPAN_ID": "601-601"}, "123": {"CONTENT": ["17", "h", "50"], "LEFT_CONTEXT": ["h", ":", "\u00ab", "Ah", "!", "si", "j'", "\u00e9tais", "riche", "\u00bb"], "RIGHT_CONTEXT": [":", "\u00ab", "C'", "est", "le", "bouquet", "\u00bb", "14", "h", ","], "START": "605", "END": "607", "SPAN_ID": "605-607"}, "124": {"CONTENT": ["le", "bouquet", "\u00bb"], "LEFT_CONTEXT": ["\u00e9tais", "riche", "\u00bb", "17", "h", "50", ":", "\u00ab", "C'", "est"], "RIGHT_CONTEXT": ["14", "h", ",", "16", "h", ":", "\u00ab", "Stuart", "little", "2"], "START": "612", "END": "614", "SPAN_ID": "612-614"}, "125": {"CONTENT": ["16", "h"], "LEFT_CONTEXT": [":", "\u00ab", "C'", "est", "le", "bouquet", "\u00bb", "14", "h", ","], "RIGHT_CONTEXT": [":", "\u00ab", "Stuart", "little", "2", "\u00bb", "14", "h", ",", "16"], "START": "618", "END": "619", "SPAN_ID": "618-619"}, "126": {"CONTENT": ["\u00ab", "Stuart", "little", "2"], "LEFT_CONTEXT": ["est", "le", "bouquet", "\u00bb", "14", "h", ",", "16", "h", ":"], "RIGHT_CONTEXT": ["\u00bb", "14", "h", ",", "16", "h", ":", "\u00ab", "Peter", "Pan"], "START": "621", "END": "624", "SPAN_ID": "621-624"}, "127": {"CONTENT": ["14", "h", ","], "LEFT_CONTEXT": ["h", ",", "16", "h", ":", "\u00ab", "Stuart", "little", "2", "\u00bb"], "RIGHT_CONTEXT": ["16", "h", ":", "\u00ab", "Peter", "Pan", "2", "\u00bb", "22", "h"], "START": "626", "END": "628", "SPAN_ID": "626-628"}, "128": {"CONTENT": ["16", "h"], "LEFT_CONTEXT": ["h", ":", "\u00ab", "Stuart", "little", "2", "\u00bb", "14", "h", ","], "RIGHT_CONTEXT": [":", "\u00ab", "Peter", "Pan", "2", "\u00bb", "22", "h", "20", ":"], "START": "629", "END": "630", "SPAN_ID": "629-630"}, "129": {"CONTENT": ["\u00ab", "Peter", "Pan", "2"], "LEFT_CONTEXT": ["Stuart", "little", "2", "\u00bb", "14", "h", ",", "16", "h", ":"], "RIGHT_CONTEXT": ["\u00bb", "22", "h", "20", ":", "\u00ab", "The", "extremists", "\u00bb", "22"], "START": "632", "END": "635", "SPAN_ID": "632-635"}, "130": {"CONTENT": ["22", "h", "20", ":", "\u00ab", "The", "extremists"], "LEFT_CONTEXT": ["h", ",", "16", "h", ":", "\u00ab", "Peter", "Pan", "2", "\u00bb"], "RIGHT_CONTEXT": ["\u00bb", "22", "h", ":", "\u00ab", "Minority", "report", "\u00bb", "DELLE", "CINEMA"], "START": "637", "END": "643", "SPAN_ID": "637-643"}, "131": {"CONTENT": ["22", "h"], "LEFT_CONTEXT": ["2", "\u00bb", "22", "h", "20", ":", "\u00ab", "The", "extremists", "\u00bb"], "RIGHT_CONTEXT": [":", "\u00ab", "Minority", "report", "\u00bb", "DELLE", "CINEMA", "DES", "CINQ", "FONTAINES"], "START": "645", "END": "646", "SPAN_ID": "645-646"}, "132": {"CONTENT": ["\u00ab", "Minority", "report"], "LEFT_CONTEXT": ["h", "20", ":", "\u00ab", "The", "extremists", "\u00bb", "22", "h", ":"], "RIGHT_CONTEXT": ["\u00bb", "DELLE", "CINEMA", "DES", "CINQ", "FONTAINES", "14", "h", "30", ":"], "START": "648", "END": "650", "SPAN_ID": "648-650"}, "133": {"CONTENT": ["DELLE", "CINEMA"], "LEFT_CONTEXT": ["The", "extremists", "\u00bb", "22", "h", ":", "\u00ab", "Minority", "report", "\u00bb"], "RIGHT_CONTEXT": ["DES", "CINQ", "FONTAINES", "14", "h", "30", ":", "\u00ab", "Brisby", "et"], "START": "652", "END": "653", "SPAN_ID": "652-653"}, "134": {"CONTENT": ["DES", "CINQ", "FONTAINES"], "LEFT_CONTEXT": ["\u00bb", "22", "h", ":", "\u00ab", "Minority", "report", "\u00bb", "DELLE", "CINEMA"], "RIGHT_CONTEXT": ["14", "h", "30", ":", "\u00ab", "Brisby", "et", "le", "secret", "de"], "START": "654", "END": "656", "SPAN_ID": "654-656"}, "135": {"CONTENT": ["14", "h", "30"], "LEFT_CONTEXT": [":", "\u00ab", "Minority", "report", "\u00bb", "DELLE", "CINEMA", "DES", "CINQ", "FONTAINES"], "RIGHT_CONTEXT": [":", "\u00ab", "Brisby", "et", "le", "secret", "de", "Nimh", "\u00bb", "17"], "START": "657", "END": "659", "SPAN_ID": "657-659"}, "136": {"CONTENT": ["\u00ab", "Brisby"], "LEFT_CONTEXT": ["\u00bb", "DELLE", "CINEMA", "DES", "CINQ", "FONTAINES", "14", "h", "30", ":"], "RIGHT_CONTEXT": ["et", "le", "secret", "de", "Nimh", "\u00bb", "17", "h", ":", "\u00ab"], "START": "661", "END": "662", "SPAN_ID": "661-662"}, "137": {"CONTENT": ["le", "secret", "de", "Nimh"], "LEFT_CONTEXT": ["DES", "CINQ", "FONTAINES", "14", "h", "30", ":", "\u00ab", "Brisby", "et"], "RIGHT_CONTEXT": ["\u00bb", "17", "h", ":", "\u00ab", "Spirit", ",", "l'", "\u00e9talon", "des"], "START": "664", "END": "667", "SPAN_ID": "664-667"}, "138": {"CONTENT": ["17", "h"], "LEFT_CONTEXT": ["30", ":", "\u00ab", "Brisby", "et", "le", "secret", "de", "Nimh", "\u00bb"], "RIGHT_CONTEXT": [":", "\u00ab", "Spirit", ",", "l'", "\u00e9talon", "des", "plaines", "\u00bb", "20"], "START": "669", "END": "670", "SPAN_ID": "669-670"}, "139": {"CONTENT": ["\u00ab", "Spirit"], "LEFT_CONTEXT": ["Brisby", "et", "le", "secret", "de", "Nimh", "\u00bb", "17", "h", ":"], "RIGHT_CONTEXT": [",", "l'", "\u00e9talon", "des", "plaines", "\u00bb", "20", "h", "30", ":"], "START": "672", "END": "673", "SPAN_ID": "672-673"}, "140": {"CONTENT": ["l'", "\u00e9talon", "des", "plaines"], "LEFT_CONTEXT": ["secret", "de", "Nimh", "\u00bb", "17", "h", ":", "\u00ab", "Spirit", ","], "RIGHT_CONTEXT": ["\u00bb", "20", "h", "30", ":", "\u00ab", "Ah", "!", "si", "j'"], "START": "675", "END": "678", "SPAN_ID": "675-678"}, "141": {"CONTENT": ["20", "h", "30"], "LEFT_CONTEXT": ["h", ":", "\u00ab", "Spirit", ",", "l'", "\u00e9talon", "des", "plaines", "\u00bb"], "RIGHT_CONTEXT": [":", "\u00ab", "Ah", "!", "si", "j'", "\u00e9tais", "riche", "\u00bb", "Jusqu'", "au"], "START": "680", "END": "682", "SPAN_ID": "680-682"}, "142": {"CONTENT": ["j'"], "LEFT_CONTEXT": ["plaines", "\u00bb", "20", "h", "30", ":", "\u00ab", "Ah", "!", "si"], "RIGHT_CONTEXT": ["\u00e9tais", "riche", "\u00bb", "Jusqu'", "au", "dimanche", "5", "janvier", ",", "les", "s\u00e9ances"], "START": "688", "END": "688", "SPAN_ID": "688-688"}, "143": {"CONTENT": ["au", "dimanche", "5", "janvier", ","], "LEFT_CONTEXT": [":", "\u00ab", "Ah", "!", "si", "j'", "\u00e9tais", "riche", "\u00bb", "Jusqu'"], "RIGHT_CONTEXT": ["les", "s\u00e9ances", "de", "14", "h", "30", "seront", "au", "tarif", "unique", "de"], "START": "693", "END": "697", "SPAN_ID": "693-697"}, "144": {"CONTENT": ["les", "s\u00e9ances", "de", "14", "h", "30"], "LEFT_CONTEXT": ["j'", "\u00e9tais", "riche", "\u00bb", "Jusqu'", "au", "dimanche", "5", "janvier", ","], "RIGHT_CONTEXT": ["seront", "au", "tarif", "unique", "de", "2,29", "\u20ac", ".", "<end>"], "START": "698", "END": "703", "SPAN_ID": "698-703"}, "145": {"CONTENT": ["au", "tarif", "unique", "de", "2,29", "\u20ac"], "LEFT_CONTEXT": ["5", "janvier", ",", "les", "s\u00e9ances", "de", "14", "h", "30", "seront"], "RIGHT_CONTEXT": [".", "<end>"], "START": "705", "END": "710", "SPAN_ID": "705-710"}, "146": {"CONTENT": ["2,29", "\u20ac", "."], "LEFT_CONTEXT": ["s\u00e9ances", "de", "14", "h", "30", "seront", "au", "tarif", "unique", "de"], "RIGHT_CONTEXT": ["<end>"], "START": "709", "END": "711", "SPAN_ID": "709-711"}, "147": {"CONTENT": ["les", "contremarques", "CE"], "LEFT_CONTEXT": ["<start>", "Exceptionnellement", ","], "RIGHT_CONTEXT": ["ne", "pourront", "pas", "\u00eatre", "accept\u00e9es", "\u00e0", "la", "caisse", "pour", "ces", "s\u00e9ances"], "START": "714", "END": "716", "SPAN_ID": "714-716"}, "148": {"CONTENT": ["la", "caisse"], "LEFT_CONTEXT": [",", "les", "contremarques", "CE", "ne", "pourront", "pas", "\u00eatre", "accept\u00e9es", "\u00e0"], "RIGHT_CONTEXT": ["pour", "ces", "s\u00e9ances", ".", "<end>"], "START": "723", "END": "724", "SPAN_ID": "723-724"}, "149": {"CONTENT": ["ces", "s\u00e9ances", "."], "LEFT_CONTEXT": ["CE", "ne", "pourront", "pas", "\u00eatre", "accept\u00e9es", "\u00e0", "la", "caisse", "pour"], "RIGHT_CONTEXT": ["<end>"], "START": "726", "END": "728", "SPAN_ID": "726-728"}}